{
	"name": "ObjectRepository",
	"layers": [
		{
			"name": "ObjectRepository",
			"overriden": 0,
			"subLayers": [],
			"instances": [
				{
					"type": "CellMarker",
					"properties": {
						"initially-visible": true,
						"initial-animation": "Default",
						"initial-frame": 0,
						"enable-collisions": false,
						"live-preview": false
					},
					"uid": 0,
					"sid": 549586502242873,
					"tags": "",
					"instanceVariables": {},
					"behaviors": {},
					"showing": true,
					"locked": false,
					"world": {
						"x": 0,
						"y": 32,
						"width": 16,
						"height": 16,
						"originX": 0,
						"originY": 0,
						"color": [
							1,
							1,
							1,
							1
						],
						"angle": 0,
						"zElevation": 0
					}
				},
				{
					"type": "Node",
					"properties": {
						"initially-visible": true,
						"initial-animation": "Default",
						"initial-frame": 0,
						"enable-collisions": false,
						"live-preview": false
					},
					"uid": 1,
					"sid": 541958628503246,
					"tags": "",
					"instanceVariables": {
						"UIDofParent": 0
					},
					"behaviors": {},
					"showing": true,
					"locked": false,
					"world": {
						"x": 8,
						"y": 8,
						"width": 16,
						"height": 16,
						"originX": 0.5,
						"originY": 0.5,
						"color": [
							1,
							1,
							1,
							1
						],
						"angle": 0,
						"zElevation": 0
					}
				},
				{
					"type": "TextFont",
					"properties": {
						"text": "Text",
						"enable-bbcode": true,
						"character-width": 11,
						"character-height": 16,
						"character-set": "ABCDEFGHIJKLMNOPQRSTUVWXYZabcdefghijklmnopqrstuvwxyz0123456789.,;:?!-_~#\"'&()[]|`\\/@°+=*$£<>%",
						"spacing-data": "[[5,\" \"],[4,\"!'|\"],[5,\"`\"],[6,\"Iil1.,;:\\\"()[]\"],[7,\"j°\"],[8,\"ABCDEFGHJKLMNOPRSTUVWXYZabcdefghkmnopqrstuvwxyz023456789?-_#&\\\\/@+=*$£<>%\"],[9,\"Q~\"]]",
						"scale": 1,
						"character-spacing": -2,
						"line-height": 0,
						"horizontal-alignment": "center",
						"vertical-alignment": "bottom",
						"wrapping": "word",
						"initially-visible": true,
						"origin": "top-left",
						"read-aloud": false
					},
					"uid": 7,
					"sid": 308740382648822,
					"tags": "",
					"instanceVariables": {},
					"behaviors": {
						"Fade": {
							"properties": {
								"fade-in-time": 0,
								"wait-time": 0,
								"fade-out-time": 1,
								"destroy": true,
								"enabled": true,
								"live-preview": false
							}
						}
					},
					"showing": true,
					"locked": false,
					"world": {
						"x": 0,
						"y": 16,
						"width": 32,
						"height": 16,
						"originX": 0,
						"originY": 0,
						"color": [
							1,
							1,
							1,
							1
						],
						"angle": 0,
						"zElevation": 0
					}
				},
				{
					"type": "Obstacle",
					"properties": {
						"initially-visible": true,
						"initial-animation": "Fence",
						"initial-frame": 0,
						"enable-collisions": true,
						"live-preview": false
					},
					"uid": 108,
					"sid": 582730951743266,
					"tags": "",
					"instanceVariables": {
						"ZOrder": 0
					},
					"behaviors": {
						"Solid": {
							"properties": {
								"enabled": true,
								"tags": ""
							}
						}
					},
					"showing": true,
					"locked": false,
					"world": {
						"x": 8,
						"y": 56,
						"width": 16,
						"height": 16,
						"originX": 0.5,
						"originY": 0.5,
						"color": [
							1,
							1,
							1,
							1
						],
						"angle": 0,
						"zElevation": 0
					}
				},
				{
					"type": "Obstacle",
					"properties": {
						"initially-visible": true,
						"initial-animation": "Fence",
						"initial-frame": 1,
						"enable-collisions": true,
						"live-preview": false
					},
					"uid": 109,
					"sid": 651769687557105,
					"tags": "",
					"instanceVariables": {
						"ZOrder": 0
					},
					"behaviors": {
						"Solid": {
							"properties": {
								"enabled": true,
								"tags": ""
							}
						}
					},
					"showing": true,
					"locked": false,
					"world": {
						"x": 24,
						"y": 56,
						"width": 16,
						"height": 16,
						"originX": 0.5,
						"originY": 0.5,
						"color": [
							1,
							1,
							1,
							1
						],
						"angle": 0,
						"zElevation": 0
					}
				},
				{
					"type": "Obstacle",
					"properties": {
						"initially-visible": true,
						"initial-animation": "Fence",
						"initial-frame": 2,
						"enable-collisions": true,
						"live-preview": false
					},
					"uid": 110,
					"sid": 270419486848215,
					"tags": "",
					"instanceVariables": {
						"ZOrder": 0
					},
					"behaviors": {
						"Solid": {
							"properties": {
								"enabled": true,
								"tags": ""
							}
						}
					},
					"showing": true,
					"locked": false,
					"world": {
						"x": 8,
						"y": 72,
						"width": 16,
						"height": 16,
						"originX": 0.5,
						"originY": 0.5,
						"color": [
							1,
							1,
							1,
							1
						],
						"angle": 0,
						"zElevation": 0
					}
				},
				{
					"type": "Obstacle",
					"properties": {
						"initially-visible": true,
						"initial-animation": "Fence",
						"initial-frame": 3,
						"enable-collisions": true,
						"live-preview": false
					},
					"uid": 111,
					"sid": 181475924782820,
					"tags": "",
					"instanceVariables": {
						"ZOrder": 0
					},
					"behaviors": {
						"Solid": {
							"properties": {
								"enabled": true,
								"tags": ""
							}
						}
					},
					"showing": true,
					"locked": false,
					"world": {
						"x": 24,
						"y": 72,
						"width": 16,
						"height": 16,
						"originX": 0.5,
						"originY": 0.5,
						"color": [
							1,
							1,
							1,
							1
						],
						"angle": 0,
						"zElevation": 0
					}
				},
				{
					"type": "Obstacle",
					"properties": {
						"initially-visible": true,
						"initial-animation": "Fence",
						"initial-frame": 4,
						"enable-collisions": true,
						"live-preview": false
					},
					"uid": 112,
					"sid": 713464332278215,
					"tags": "",
					"instanceVariables": {
						"ZOrder": 0
					},
					"behaviors": {
						"Solid": {
							"properties": {
								"enabled": true,
								"tags": ""
							}
						}
					},
					"showing": true,
					"locked": false,
					"world": {
						"x": 8,
						"y": 88,
						"width": 16,
						"height": 16,
						"originX": 0.5,
						"originY": 0.5,
						"color": [
							1,
							1,
							1,
							1
						],
						"angle": 0,
						"zElevation": 0
					}
				},
				{
					"type": "Obstacle",
					"properties": {
						"initially-visible": true,
						"initial-animation": "Fence",
						"initial-frame": 5,
						"enable-collisions": true,
						"live-preview": false
					},
					"uid": 113,
					"sid": 140341354387654,
					"tags": "",
					"instanceVariables": {
						"ZOrder": 0
					},
					"behaviors": {
						"Solid": {
							"properties": {
								"enabled": true,
								"tags": ""
							}
						}
					},
					"showing": true,
					"locked": false,
					"world": {
						"x": 24,
						"y": 88,
						"width": 16,
						"height": 16,
						"originX": 0.5,
						"originY": 0.5,
						"color": [
							1,
							1,
							1,
							1
						],
						"angle": 0,
						"zElevation": 0
					}
				},
				{
					"type": "Obstacle",
					"properties": {
						"initially-visible": true,
						"initial-animation": "Fence",
						"initial-frame": 6,
						"enable-collisions": true,
						"live-preview": false
					},
					"uid": 114,
					"sid": 485349353305653,
					"tags": "",
					"instanceVariables": {
						"ZOrder": 0
					},
					"behaviors": {
						"Solid": {
							"properties": {
								"enabled": true,
								"tags": ""
							}
						}
					},
					"showing": true,
					"locked": false,
					"world": {
						"x": 8,
						"y": 104,
						"width": 16,
						"height": 16,
						"originX": 0.5,
						"originY": 0.5,
						"color": [
							1,
							1,
							1,
							1
						],
						"angle": 0,
						"zElevation": 0
					}
				},
				{
					"type": "Obstacle",
					"properties": {
						"initially-visible": true,
						"initial-animation": "Fence",
						"initial-frame": 7,
						"enable-collisions": true,
						"live-preview": false
					},
					"uid": 115,
					"sid": 144802587450620,
					"tags": "",
					"instanceVariables": {
						"ZOrder": 0
					},
					"behaviors": {
						"Solid": {
							"properties": {
								"enabled": true,
								"tags": ""
							}
						}
					},
					"showing": true,
					"locked": false,
					"world": {
						"x": 24,
						"y": 104,
						"width": 16,
						"height": 16,
						"originX": 0.5,
						"originY": 0.5,
						"color": [
							1,
							1,
							1,
							1
						],
						"angle": 0,
						"zElevation": 0
					}
				},
				{
					"type": "Obstacle",
					"properties": {
						"initially-visible": true,
						"initial-animation": "Fence",
						"initial-frame": 8,
						"enable-collisions": true,
						"live-preview": false
					},
					"uid": 116,
					"sid": 653922722888724,
					"tags": "",
					"instanceVariables": {
						"ZOrder": 0
					},
					"behaviors": {
						"Solid": {
							"properties": {
								"enabled": true,
								"tags": ""
							}
						}
					},
					"showing": true,
					"locked": false,
					"world": {
						"x": 40,
						"y": 56,
						"width": 16,
						"height": 16,
						"originX": 0.5,
						"originY": 0.5,
						"color": [
							1,
							1,
							1,
							1
						],
						"angle": 0,
						"zElevation": 0
					}
				},
				{
					"type": "Obstacle",
					"properties": {
						"initially-visible": true,
						"initial-animation": "Fence",
						"initial-frame": 10,
						"enable-collisions": true,
						"live-preview": false
					},
					"uid": 117,
					"sid": 998418593599725,
					"tags": "",
					"instanceVariables": {
						"ZOrder": 0
					},
					"behaviors": {
						"Solid": {
							"properties": {
								"enabled": true,
								"tags": ""
							}
						}
					},
					"showing": true,
					"locked": false,
					"world": {
						"x": 56,
						"y": 56,
						"width": 16,
						"height": 16,
						"originX": 0.5,
						"originY": 0.5,
						"color": [
							1,
							1,
							1,
							1
						],
						"angle": 0,
						"zElevation": 0
					}
				},
				{
					"type": "Obstacle",
					"properties": {
						"initially-visible": true,
						"initial-animation": "Fence",
						"initial-frame": 9,
						"enable-collisions": true,
						"live-preview": false
					},
					"uid": 118,
					"sid": 901566605360869,
					"tags": "",
					"instanceVariables": {
						"ZOrder": 0
					},
					"behaviors": {
						"Solid": {
							"properties": {
								"enabled": true,
								"tags": ""
							}
						}
					},
					"showing": true,
					"locked": false,
					"world": {
						"x": 40,
						"y": 72,
						"width": 16,
						"height": 16,
						"originX": 0.5,
						"originY": 0.5,
						"color": [
							1,
							1,
							1,
							1
						],
						"angle": 0,
						"zElevation": 0
					}
				},
				{
					"type": "Obstacle",
					"properties": {
						"initially-visible": true,
						"initial-animation": "Fence",
						"initial-frame": 11,
						"enable-collisions": true,
						"live-preview": false
					},
					"uid": 119,
					"sid": 725707363957635,
					"tags": "",
					"instanceVariables": {
						"ZOrder": 0
					},
					"behaviors": {
						"Solid": {
							"properties": {
								"enabled": true,
								"tags": ""
							}
						}
					},
					"showing": true,
					"locked": false,
					"world": {
						"x": 56,
						"y": 72,
						"width": 16,
						"height": 16,
						"originX": 0.5,
						"originY": 0.5,
						"color": [
							1,
							1,
							1,
							1
						],
						"angle": 0,
						"zElevation": 0
					}
				},
				{
					"type": "TextBubble",
					"properties": {
						"initially-visible": true,
						"initial-animation": "FollowMe",
						"initial-frame": 0,
						"enable-collisions": false,
						"live-preview": false
					},
					"uid": 97,
					"sid": 785673954627690,
					"tags": "",
					"instanceVariables": {},
					"behaviors": {
						"Tween": {
							"properties": {
								"enabled": true
							}
						},
						"Timer": {
							"properties": {}
						}
					},
					"showing": true,
					"locked": false,
					"world": {
						"x": 18,
						"y": 45,
						"width": 43,
						"height": 11,
						"originX": 0,
						"originY": 1,
						"color": [
							1,
							1,
							1,
							1
						],
						"angle": 0,
						"zElevation": 0
					}
				},
				{
					"type": "Leaf",
					"properties": {
						"initially-visible": true,
						"initial-animation": "Default",
						"initial-frame": 0,
						"enable-collisions": false,
						"live-preview": false
					},
					"uid": 96,
					"sid": 267830195236078,
					"tags": "",
					"instanceVariables": {},
					"behaviors": {
						"Bullet": {
							"properties": {
								"speed": 32,
								"acceleration": 0,
								"gravity": 0,
								"bounce-off-solids": false,
								"set-angle": false,
								"step": false,
								"enabled": true
							}
						}
					},
					"showing": true,
					"locked": false,
					"world": {
						"x": 40,
						"y": 8,
						"width": 4,
						"height": 4,
						"originX": 0.5,
						"originY": 0.5,
						"color": [
							1,
							1,
							1,
							1
						],
						"angle": 0,
						"zElevation": 0
					}
				},
				{
					"type": "NodeLine",
					"properties": {
						"left-margin": 4,
						"right-margin": 4,
						"top-margin": 0,
						"bottom-margin": 0,
						"edges": "tile",
						"fill": "tile",
						"initially-visible": true,
						"origin": "left",
						"seams": "exact"
					},
					"uid": 95,
					"sid": 995863081625173,
					"tags": "",
					"instanceVariables": {
						"UIDofParent": 0
					},
					"behaviors": {},
					"showing": true,
					"locked": false,
					"world": {
						"x": 16,
						"y": 8,
						"width": 16,
						"height": 4,
						"originX": 0,
						"originY": 0.5,
						"color": [
							1,
							1,
							1,
							1
						],
						"angle": 0,
						"zElevation": 0
					}
				},
				{
					"type": "Pop",
					"properties": {
						"initially-visible": true,
						"initial-animation": "Default",
						"initial-frame": 0,
						"enable-collisions": false,
						"live-preview": false
					},
					"uid": 102,
					"sid": 470333838964659,
					"tags": "",
					"instanceVariables": {},
					"behaviors": {
						"Bullet": {
							"properties": {
								"speed": 64,
								"acceleration": 0,
								"gravity": 0,
								"bounce-off-solids": false,
								"set-angle": false,
								"step": false,
								"enabled": true
							}
						}
					},
					"showing": true,
					"locked": false,
					"world": {
						"x": 56,
						"y": 8,
						"width": 16,
						"height": 16,
						"originX": 0.5,
						"originY": 0.5,
						"color": [
							1,
							1,
							1,
							1
						],
						"angle": 0,
						"zElevation": 0
					}
				},
				{
					"type": "PlayerGraphics",
					"properties": {
						"initially-visible": true,
						"initial-animation": "Idle90",
						"initial-frame": 0,
						"enable-collisions": false,
						"live-preview": false
					},
					"uid": 2,
					"sid": 746279022478962,
					"tags": "",
					"instanceVariables": {
						"ZOrder": 0,
						"AngleOfMotion": 90
					},
					"behaviors": {},
					"showing": true,
					"locked": false,
					"world": {
						"x": 76,
						"y": 20,
						"width": 24,
						"height": 24,
						"originX": 0.5,
						"originY": 0.8333333333333334,
						"color": [
							1,
							1,
							1,
							1
						],
						"angle": 0,
						"zElevation": 0
					}
				},
				{
					"type": "Sprite",
					"properties": {
						"initially-visible": true,
						"initial-animation": "Default",
						"initial-frame": 0,
						"enable-collisions": false,
						"live-preview": false
					},
					"uid": 103,
					"sid": 515140170023474,
					"tags": "",
					"instanceVariables": {},
					"behaviors": {},
					"showing": true,
					"locked": false,
					"world": {
						"x": 95,
						"y": 74,
						"width": 16,
						"height": 16,
						"originX": 0.5,
						"originY": 0.5,
						"color": [
							1,
							1,
							1,
							1
						],
						"angle": 0,
						"zElevation": 0
					}
				}
			],
			"sid": 118632593814172,
			"effectTypes": [],
			"isInitiallyVisible": true,
			"isInitiallyInteractive": true,
			"isHTMLElementsLayer": false,
			"color": [
				1,
				1,
				1,
				1
			],
			"backgroundColor": [
				0.3686274509803922,
				0.3686274509803922,
				0.3686274509803922,
				1
			],
			"isTransparent": false,
			"parallaxX": 1,
			"parallaxY": 1,
			"scaleRate": 1,
			"forceOwnTexture": false,
			"renderingMode": "3d",
			"drawOrder": "z-order",
			"useRenderCells": false,
			"blendMode": "normal",
			"zElevation": 0,
			"global": false
		}
	],
	"scene-graphs-folder-root": {
		"items": [],
		"subfolders": []
	},
	"sid": 423021543579916,
	"nonworld-instances": [],
	"effectTypes": [],
	"width": 640,
	"height": 360,
	"unboundedScrolling": false,
	"vpX": 0.5,
	"vpY": 0.5,
	"projection": "perspective",
	"eventSheet": null
}