{
	"name": "Smoke",
	"plugin-id": "Sprite",
	"sid": 286357821091298,
	"isGlobal": false,
	"instanceVariables": [],
	"behaviorTypes": [
		{
			"behaviorId": "Tween",
			"name": "Tween",
			"sid": 697365601720235
		}
	],
	"effectTypes": [],
	"animations": {
		"items": [
			{
				"frames": [
					{
						"width": 80,
						"height": 80,
						"originX": 0.5,
						"originY": 0.5,
						"originalSource": "",
						"exportFormat": "lossless",
						"exportQuality": 0.8,
						"imageSpriteId": 2754176,
						"useCollisionPoly": true,
						"duration": 1,
						"tag": ""
					}
				],
				"sid": 835944750929598,
				"name": "Animation 1",
				"isLooping": false,
				"isPingPong": false,
				"repeatCount": 1,
				"repeatTo": 0,
				"speed": 0
			}
		],
		"subfolders": []
	}
}