{
	"name": "CupShadow",
	"plugin-id": "Sprite",
	"sid": 342270674265127,
	"isGlobal": false,
	"instanceVariables": [
		{
			"name": "Index",
			"type": "number",
			"desc": "",
			"show": true,
			"sid": 303398670112789
		},
		{
			"name": "PreviousX",
			"type": "number",
			"desc": "",
			"show": true,
			"sid": 588873583349426
		},
		{
			"name": "PreviousY",
			"type": "number",
			"desc": "",
			"show": true,
			"sid": 511519409912801
		}
	],
	"behaviorTypes": [
		{
			"behaviorId": "Tween",
			"name": "Tween",
			"sid": 299987434182786
		}
	],
	"effectTypes": [],
	"animations": {
		"items": [
			{
				"frames": [
					{
						"width": 640,
						"height": 256,
						"originX": 0.39375,
						"originY": 0.765625,
						"originalSource": "",
						"exportFormat": "lossless",
						"exportQuality": 0.8,
						"imageSpriteId": 1882005,
						"useCollisionPoly": true,
						"duration": 1,
						"tag": ""
					}
				],
				"sid": 361056533782522,
				"name": "Default",
				"isLooping": false,
				"isPingPong": false,
				"repeatCount": 1,
				"repeatTo": 0,
				"speed": 0
			}
		],
		"subfolders": []
	}
}