{
	"name": "Board",
	"plugin-id": "Shape3D",
	"sid": 726305013524322,
	"isGlobal": false,
	"instanceVariables": [],
	"behaviorTypes": [],
	"effectTypes": [],
	"animations": {
		"items": [
			{
				"frames": [
					{
						"width": 2,
						"height": 16,
						"originX": 0.5,
						"originY": 0.5,
						"originalSource": "",
						"exportFormat": "lossless",
						"exportQuality": 0.8,
						"imageSpriteId": 7973081,
						"useCollisionPoly": true,
						"duration": 1,
						"tag": ""
					},
					{
						"width": 2,
						"height": 16,
						"originX": 0.5,
						"originY": 0.5,
						"originalSource": "",
						"exportFormat": "lossless",
						"exportQuality": 0.8,
						"imageSpriteId": 2755208,
						"useCollisionPoly": true,
						"duration": 1,
						"tag": ""
					},
					{
						"width": 16,
						"height": 12,
						"originX": 0.5,
						"originY": 0.5,
						"originalSource": "",
						"exportFormat": "lossless",
						"exportQuality": 0.8,
						"imageSpriteId": 7528729,
						"useCollisionPoly": true,
						"duration": 1,
						"tag": ""
					},
					{
						"width": 16,
						"height": 12,
						"originX": 0.5,
						"originY": 0.5,
						"originalSource": "",
						"exportFormat": "lossless",
						"exportQuality": 0.8,
						"imageSpriteId": 375227,
						"useCollisionPoly": true,
						"duration": 1,
						"tag": ""
					},
					{
						"width": 2,
						"height": 12,
						"originX": 0.5,
						"originY": 0.5,
						"originalSource": "",
						"exportFormat": "lossless",
						"exportQuality": 0.8,
						"imageSpriteId": 4324746,
						"useCollisionPoly": true,
						"duration": 1,
						"tag": ""
					},
					{
						"width": 2,
						"height": 12,
						"originX": 0.5,
						"originY": 0.5,
						"originalSource": "",
						"exportFormat": "lossless",
						"exportQuality": 0.8,
						"imageSpriteId": 980840,
						"useCollisionPoly": true,
						"duration": 1,
						"tag": ""
					}
				],
				"sid": 530172549514070,
				"name": "Animation 1",
				"isLooping": false,
				"isPingPong": false,
				"repeatCount": 1,
				"repeatTo": 0,
				"speed": 0
			}
		],
		"subfolders": []
	}
}