{
	"name": "GridBlock",
	"plugin-id": "NinePatch",
	"sid": 309164952320836,
	"isGlobal": false,
	"instanceVariables": [
		{
			"name": "Index",
			"type": "number",
			"desc": "",
			"sid": 335820601519183
		},
		{
			"name": "Snapped",
			"type": "boolean",
			"desc": "",
			"sid": 445777766040154
		}
	],
	"behaviorTypes": [],
	"effectTypes": [],
	"image": {
		"width": 32,
		"height": 32,
		"originX": 0.5,
		"originY": 0.5,
		"originalSource": "",
		"exportFormat": "png",
		"exportQuality": 0.8,
		"imageSpriteId": 7293961,
		"useCollisionPoly": true
	}
}