{
	"name": "Game",
	"layers": [
		{
			"name": "Clouds",
			"overriden": 0,
			"subLayers": [],
			"instances": [
				{
					"type": "Clouds",
					"properties": {
						"initially-visible": true,
						"origin": "top-left",
						"wrap-horizontal": "repeat",
						"wrap-vertical": "repeat",
						"image-offset-x": 0,
						"image-offset-y": 0,
						"image-scale-x": 1,
						"image-scale-y": 1,
						"image-angle": 0,
						"enable-tile-randomization": false,
						"x-random": 1,
						"y-random": 1,
						"angle-random": 1,
						"blend-margin-x": 0.1,
						"blend-margin-y": 0.1
					},
					"uid": 22,
					"sid": 444010944836480,
					"tags": "",
					"instanceVariables": {},
					"behaviors": {},
					"instanceFolderItem": {
						"sid": 444010944836480,
						"expanded": true,
						"folderName": "",
						"indexInFolder": -1,
						"folderNestingLevel": -1
					},
					"showing": true,
					"locked": false,
					"world": {
						"x": -34,
						"y": -558,
						"width": 1332,
						"height": 684,
						"originX": 0,
						"originY": 0,
						"color": [
							1,
							1,
							1,
							0.75
						],
						"angle": 0,
						"zElevation": 0
					}
				},
				{
					"type": "Clouds",
					"properties": {
						"initially-visible": true,
						"origin": "top-left",
						"wrap-horizontal": "repeat",
						"wrap-vertical": "repeat",
						"image-offset-x": 720,
						"image-offset-y": 0,
						"image-scale-x": 1,
						"image-scale-y": 1,
						"image-angle": 0,
						"enable-tile-randomization": false,
						"x-random": 1,
						"y-random": 1,
						"angle-random": 1,
						"blend-margin-x": 0.1,
						"blend-margin-y": 0.1
					},
					"uid": 23,
					"sid": 699302977487148,
					"tags": "",
					"instanceVariables": {},
					"behaviors": {},
					"instanceFolderItem": {
						"sid": 699302977487148,
						"expanded": true,
						"folderName": "",
						"indexInFolder": -1,
						"folderNestingLevel": -1
					},
					"showing": true,
					"locked": false,
					"world": {
						"x": 0,
						"y": 144,
						"width": 1280,
						"height": 576,
						"originX": 0,
						"originY": 0,
						"color": [
							1,
							1,
							1,
							0.75
						],
						"angle": 0,
						"zElevation": 0
					}
				}
			],
			"sid": 333198338575570,
			"effectTypes": [],
			"isInitiallyVisible": true,
			"isInitiallyInteractive": true,
			"isHTMLElementsLayer": false,
			"color": [
				1,
				1,
				1,
				1
			],
			"backgroundColor": [
				0.30980392156862746,
				0.4823529411764706,
				0.6705882352941176,
				1
			],
			"isTransparent": false,
			"parallaxX": 1,
			"parallaxY": 1,
			"scaleRate": 1,
			"forceOwnTexture": false,
			"renderingMode": "3d",
			"drawOrder": "z-order",
			"useRenderCells": false,
			"blendMode": "normal",
			"zElevation": 0,
			"global": false
		},
		{
			"name": "Background",
			"overriden": 0,
			"subLayers": [],
			"instances": [
				{
					"type": "Background",
					"properties": {
						"initially-visible": true,
						"initial-animation": "Animation 1",
						"initial-frame": 0,
						"enable-collisions": true,
						"live-preview": false
					},
					"uid": 19,
					"sid": 523008353976276,
					"tags": "",
					"instanceVariables": {},
					"behaviors": {},
					"instanceFolderItem": {
						"sid": 523008353976276,
						"expanded": true,
						"folderName": "",
						"indexInFolder": -1,
						"folderNestingLevel": -1
					},
					"showing": true,
					"locked": false,
					"world": {
						"x": 414,
						"y": 119.75,
						"width": 702,
						"height": 684,
						"originX": 0.17806267806267806,
						"originY": 0.1736111111111111,
						"color": [
							1,
							1,
							1,
							1
						],
						"angle": 0,
						"zElevation": 0
					}
				}
			],
			"sid": 601765745354989,
			"effectTypes": [],
			"isInitiallyVisible": true,
			"isInitiallyInteractive": true,
			"isHTMLElementsLayer": false,
			"color": [
				1,
				1,
				1,
				1
			],
			"backgroundColor": [
				0.3686274509803922,
				0.3686274509803922,
				0.3686274509803922,
				1
			],
			"isTransparent": true,
			"parallaxX": 1,
			"parallaxY": 1,
			"scaleRate": 1,
			"forceOwnTexture": false,
			"renderingMode": "3d",
			"drawOrder": "z-order",
			"useRenderCells": false,
			"blendMode": "normal",
			"zElevation": 0,
			"global": false
		},
		{
			"name": "World",
			"overriden": 0,
			"subLayers": [],
			"instances": [
				{
					"type": "DecorationRight",
					"properties": {
						"initially-visible": true,
						"initial-animation": "Animation 1",
						"initial-frame": 0,
						"enable-collisions": true,
						"live-preview": false
					},
					"uid": 17,
					"sid": 242466491721648,
					"tags": "",
					"instanceVariables": {},
					"behaviors": {},
					"instanceFolderItem": {
						"sid": 242466491721648,
						"expanded": true,
						"folderName": "",
						"indexInFolder": -1,
						"folderNestingLevel": -1
					},
					"showing": true,
					"locked": false,
					"world": {
						"x": 1314,
						"y": -18.20196353436185,
						"width": 358,
						"height": 810,
						"originX": 0.9972067039106145,
						"originY": -0.011220196353436185,
						"color": [
							1,
							1,
							1,
							1
						],
						"angle": 0,
						"zElevation": 0
					}
				},
				{
					"type": "DecorationLeft",
					"properties": {
						"initially-visible": true,
						"initial-animation": "Animation 1",
						"initial-frame": 0,
						"enable-collisions": true,
						"live-preview": false
					},
					"uid": 14,
					"sid": 166764967537089,
					"tags": "",
					"instanceVariables": {},
					"behaviors": {},
					"instanceFolderItem": {
						"sid": 166764967537089,
						"expanded": true,
						"folderName": "",
						"indexInFolder": -1,
						"folderNestingLevel": -1
					},
					"showing": true,
					"locked": false,
					"world": {
						"x": 108,
						"y": 144,
						"width": 358,
						"height": 756.0000000000001,
						"originX": 0.39664804469273746,
						"originY": 0.1640953716690042,
						"color": [
							1,
							1,
							1,
							1
						],
						"angle": 0,
						"zElevation": 0
					}
				},
				{
					"type": "Player",
					"properties": {
						"initially-visible": false,
						"initial-animation": "Normal",
						"initial-frame": 0,
						"enable-collisions": true,
						"live-preview": false
					},
					"uid": 2,
					"sid": 227491520483606,
					"tags": "",
					"instanceVariables": {
						"bucketFull": false,
						"climbing": false,
						"climbSpeed": 65,
						"doneClimbing": false
					},
					"behaviors": {
						"Platform": {
							"properties": {
								"max-speed": 100,
								"acceleration": 1500,
								"deceleration": 1500,
								"jump-strength": 420,
								"gravity": 1000,
								"max-fall-speed": 1000,
								"double-jump": false,
								"jump-sustain": 0,
								"default-controls": false,
								"enabled": true
							}
						},
						"Tween": {
							"properties": {
								"enabled": true
							}
						}
					},
					"sceneGraphData": {
						"parent-uid": null,
						"uid": 2,
						"children": [
							{
								"uid": 11,
								"flags": {
									"x": true,
									"y": true,
									"z": false,
									"w": true,
									"h": false,
									"a": false,
									"o": false,
									"v": false,
									"d": true,
									"sm": "normal"
								}
							}
						],
						"flags": {
							"x": true,
							"y": true,
							"z": true,
							"w": true,
							"h": true,
							"a": true,
							"o": false,
							"v": false,
							"d": true,
							"sm": "normal"
						},
						"preview": {
							"transformX": 0,
							"transformY": 0,
							"transformZElevation": 0,
							"transformW": 0,
							"transformH": 0,
							"transformA": 0,
							"transformSX": 0,
							"transformSY": 0,
							"transformO": 0,
							"previewSceneGraph": false
						}
					},
					"instanceFolderItem": {
						"sid": 227491520483606,
						"expanded": true,
						"folderName": "",
						"indexInFolder": -1,
						"folderNestingLevel": -1
					},
					"showing": true,
					"locked": false,
					"world": {
						"x": 432,
						"y": 684,
						"width": 24,
						"height": 24,
						"originX": 0.5,
						"originY": 1,
						"color": [
							1,
							1,
							1,
							1
						],
						"angle": 0,
						"zElevation": 0
					}
				},
				{
					"type": "Ground",
					"properties": {
						"left-margin": 18,
						"right-margin": 18,
						"top-margin": 72,
						"bottom-margin": 0,
						"edges": "tile",
						"fill": "tile",
						"initially-visible": true,
						"origin": "top-left",
						"seams": "overlap"
					},
					"uid": 18,
					"sid": 296944048224040,
					"tags": "",
					"instanceVariables": {},
					"behaviors": {
						"Solid": {
							"properties": {
								"enabled": true,
								"tags": "geometry"
							}
						}
					},
					"instanceFolderItem": {
						"sid": 296944048224040,
						"expanded": true,
						"folderName": "",
						"indexInFolder": -1,
						"folderNestingLevel": -1
					},
					"showing": true,
					"locked": false,
					"world": {
						"x": 270,
						"y": 684,
						"width": 738,
						"height": 72,
						"originX": 0,
						"originY": 0,
						"color": [
							1,
							1,
							1,
							1
						],
						"angle": 0,
						"zElevation": 0
					}
				},
				{
					"type": "Ground",
					"properties": {
						"left-margin": 18,
						"right-margin": 18,
						"top-margin": 72,
						"bottom-margin": 0,
						"edges": "tile",
						"fill": "tile",
						"initially-visible": true,
						"origin": "top-left",
						"seams": "overlap"
					},
					"uid": 8,
					"sid": 393554155855284,
					"tags": "",
					"instanceVariables": {},
					"behaviors": {
						"Solid": {
							"properties": {
								"enabled": true,
								"tags": ""
							}
						}
					},
					"instanceFolderItem": {
						"sid": 393554155855284,
						"expanded": true,
						"folderName": "",
						"indexInFolder": -1,
						"folderNestingLevel": -1
					},
					"showing": true,
					"locked": false,
					"world": {
						"x": -36,
						"y": 684,
						"width": 198,
						"height": 72,
						"originX": 0,
						"originY": 0,
						"color": [
							1,
							1,
							1,
							1
						],
						"angle": 0,
						"zElevation": 0
					}
				},
				{
					"type": "Ground",
					"properties": {
						"left-margin": 18,
						"right-margin": 18,
						"top-margin": 72,
						"bottom-margin": 0,
						"edges": "tile",
						"fill": "tile",
						"initially-visible": true,
						"origin": "top-left",
						"seams": "overlap"
					},
					"uid": 16,
					"sid": 933492741915691,
					"tags": "",
					"instanceVariables": {},
					"behaviors": {
						"Solid": {
							"properties": {
								"enabled": true,
								"tags": ""
							}
						}
					},
					"instanceFolderItem": {
						"sid": 933492741915691,
						"expanded": true,
						"folderName": "",
						"indexInFolder": -1,
						"folderNestingLevel": -1
					},
					"showing": true,
					"locked": false,
					"world": {
						"x": 1116,
						"y": 684,
						"width": 198,
						"height": 72,
						"originX": 0,
						"originY": 0,
						"color": [
							1,
							1,
							1,
							1
						],
						"angle": 0,
						"zElevation": 0
					}
				},
				{
					"type": "PlatLeft",
					"properties": {
						"left-margin": 18,
						"right-margin": 18,
						"top-margin": 18,
						"bottom-margin": 0,
						"edges": "tile",
						"fill": "tile",
						"initially-visible": true,
						"origin": "left",
						"seams": "overlap"
					},
					"uid": 31,
					"sid": 799293778250217,
					"tags": "",
					"instanceVariables": {},
					"behaviors": {
						"Tween": {
							"properties": {
								"enabled": true
							}
						},
						"Solid": {
							"properties": {
								"enabled": true,
								"tags": "geometry"
							}
						}
					},
					"sceneGraphData": {
						"parent-uid": null,
						"uid": 31,
						"children": [
							{
								"uid": 34,
								"flags": {
									"x": true,
									"y": true,
									"z": true,
									"w": true,
									"h": true,
									"a": true,
									"o": false,
									"v": false,
									"d": true,
									"sm": "normal"
								}
							},
							{
								"uid": 35,
								"flags": {
									"x": true,
									"y": true,
									"z": true,
									"w": true,
									"h": true,
									"a": true,
									"o": false,
									"v": false,
									"d": true,
									"sm": "normal"
								}
							},
							{
								"uid": 46,
								"flags": {
									"x": true,
									"y": true,
									"z": true,
									"w": true,
									"h": true,
									"a": true,
									"o": false,
									"v": false,
									"d": true,
									"sm": "normal"
								}
							},
							{
								"uid": 62,
								"flags": {
									"x": true,
									"y": true,
									"z": true,
									"w": true,
									"h": true,
									"a": true,
									"o": false,
									"v": false,
									"d": true,
									"sm": "normal"
								}
							}
						],
						"flags": {
							"x": true,
							"y": true,
							"z": true,
							"w": true,
							"h": true,
							"a": true,
							"o": false,
							"v": false,
							"d": true,
							"sm": "normal"
						},
						"preview": {
							"transformX": 0,
							"transformY": 0,
							"transformZElevation": 0,
							"transformW": 0,
							"transformH": 0,
							"transformA": 0,
							"transformSX": 0,
							"transformSY": 0,
							"transformO": 0,
							"previewSceneGraph": false
						}
					},
					"instanceFolderItem": {
						"sid": 799293778250217,
						"expanded": true,
						"folderName": "",
						"indexInFolder": -1,
						"folderNestingLevel": -1
					},
					"showing": true,
					"locked": false,
					"world": {
						"x": 288,
						"y": 579,
						"width": 648,
						"height": 18,
						"originX": 0,
						"originY": 0.5,
						"color": [
							1,
							1,
							1,
							1
						],
						"angle": 0,
						"zElevation": 0
					}
				},
				{
					"type": "PlatRight",
					"properties": {
						"left-margin": 18,
						"right-margin": 18,
						"top-margin": 18,
						"bottom-margin": 0,
						"edges": "tile",
						"fill": "tile",
						"initially-visible": true,
						"origin": "right",
						"seams": "overlap"
					},
					"uid": 4,
					"sid": 122994939475319,
					"tags": "",
					"instanceVariables": {},
					"behaviors": {
						"Tween": {
							"properties": {
								"enabled": true
							}
						},
						"Solid": {
							"properties": {
								"enabled": true,
								"tags": "geometry"
							}
						}
					},
					"sceneGraphData": {
						"parent-uid": null,
						"uid": 4,
						"children": [
							{
								"uid": 36,
								"flags": {
									"x": true,
									"y": true,
									"z": true,
									"w": true,
									"h": true,
									"a": true,
									"o": false,
									"v": false,
									"d": true,
									"sm": "normal"
								}
							},
							{
								"uid": 50,
								"flags": {
									"x": true,
									"y": true,
									"z": true,
									"w": true,
									"h": true,
									"a": true,
									"o": false,
									"v": false,
									"d": true,
									"sm": "normal"
								}
							},
							{
								"uid": 70,
								"flags": {
									"x": true,
									"y": true,
									"z": true,
									"w": true,
									"h": true,
									"a": true,
									"o": false,
									"v": false,
									"d": true,
									"sm": "normal"
								}
							},
							{
								"uid": 71,
								"flags": {
									"x": true,
									"y": true,
									"z": true,
									"w": true,
									"h": true,
									"a": true,
									"o": false,
									"v": false,
									"d": true,
									"sm": "normal"
								}
							}
						],
						"flags": {
							"x": true,
							"y": true,
							"z": true,
							"w": true,
							"h": true,
							"a": true,
							"o": false,
							"v": false,
							"d": true,
							"sm": "normal"
						},
						"preview": {
							"transformX": 0,
							"transformY": 0,
							"transformZElevation": 0,
							"transformW": 0,
							"transformH": 0,
							"transformA": 0,
							"transformSX": 0,
							"transformSY": 0,
							"transformO": 0,
							"previewSceneGraph": false
						}
					},
					"instanceFolderItem": {
						"sid": 122994939475319,
						"expanded": true,
						"folderName": "",
						"indexInFolder": -1,
						"folderNestingLevel": -1
					},
					"showing": true,
					"locked": false,
					"world": {
						"x": 990,
						"y": 465,
						"width": 648,
						"height": 18,
						"originX": 1,
						"originY": 0.5,
						"color": [
							1,
							1,
							1,
							1
						],
						"angle": 0,
						"zElevation": 0
					}
				},
				{
					"type": "PlatLeft",
					"properties": {
						"left-margin": 18,
						"right-margin": 18,
						"top-margin": 18,
						"bottom-margin": 0,
						"edges": "tile",
						"fill": "tile",
						"initially-visible": true,
						"origin": "left",
						"seams": "overlap"
					},
					"uid": 5,
					"sid": 989312397854724,
					"tags": "",
					"instanceVariables": {},
					"behaviors": {
						"Tween": {
							"properties": {
								"enabled": true
							}
						},
						"Solid": {
							"properties": {
								"enabled": true,
								"tags": "geometry"
							}
						}
					},
					"sceneGraphData": {
						"parent-uid": null,
						"uid": 5,
						"children": [
							{
								"uid": 37,
								"flags": {
									"x": true,
									"y": true,
									"z": true,
									"w": true,
									"h": true,
									"a": true,
									"o": false,
									"v": false,
									"d": true,
									"sm": "normal"
								}
							},
							{
								"uid": 38,
								"flags": {
									"x": true,
									"y": true,
									"z": true,
									"w": true,
									"h": true,
									"a": true,
									"o": false,
									"v": false,
									"d": true,
									"sm": "normal"
								}
							},
							{
								"uid": 51,
								"flags": {
									"x": true,
									"y": true,
									"z": true,
									"w": true,
									"h": true,
									"a": true,
									"o": false,
									"v": false,
									"d": true,
									"sm": "normal"
								}
							},
							{
								"uid": 72,
								"flags": {
									"x": true,
									"y": true,
									"z": true,
									"w": true,
									"h": true,
									"a": true,
									"o": false,
									"v": false,
									"d": true,
									"sm": "normal"
								}
							},
							{
								"uid": 73,
								"flags": {
									"x": true,
									"y": true,
									"z": true,
									"w": true,
									"h": true,
									"a": true,
									"o": false,
									"v": false,
									"d": true,
									"sm": "normal"
								}
							}
						],
						"flags": {
							"x": true,
							"y": true,
							"z": true,
							"w": true,
							"h": true,
							"a": true,
							"o": false,
							"v": false,
							"d": true,
							"sm": "normal"
						},
						"preview": {
							"transformX": 0,
							"transformY": 0,
							"transformZElevation": 0,
							"transformW": 0,
							"transformH": 0,
							"transformA": 0,
							"transformSX": 0,
							"transformSY": 0,
							"transformO": 0,
							"previewSceneGraph": false
						}
					},
					"instanceFolderItem": {
						"sid": 989312397854724,
						"expanded": true,
						"folderName": "",
						"indexInFolder": -1,
						"folderNestingLevel": -1
					},
					"showing": true,
					"locked": false,
					"world": {
						"x": 288,
						"y": 351,
						"width": 648,
						"height": 18,
						"originX": 0,
						"originY": 0.5,
						"color": [
							1,
							1,
							1,
							1
						],
						"angle": 0,
						"zElevation": 0
					}
				},
				{
					"type": "PlatRight",
					"properties": {
						"left-margin": 18,
						"right-margin": 18,
						"top-margin": 18,
						"bottom-margin": 0,
						"edges": "tile",
						"fill": "tile",
						"initially-visible": true,
						"origin": "right",
						"seams": "overlap"
					},
					"uid": 6,
					"sid": 610675141839358,
					"tags": "",
					"instanceVariables": {},
					"behaviors": {
						"Tween": {
							"properties": {
								"enabled": true
							}
						},
						"Solid": {
							"properties": {
								"enabled": true,
								"tags": "geometry"
							}
						}
					},
					"sceneGraphData": {
						"parent-uid": null,
						"uid": 6,
						"children": [
							{
								"uid": 39,
								"flags": {
									"x": true,
									"y": true,
									"z": true,
									"w": true,
									"h": true,
									"a": true,
									"o": false,
									"v": false,
									"d": true,
									"sm": "normal"
								}
							},
							{
								"uid": 52,
								"flags": {
									"x": true,
									"y": true,
									"z": true,
									"w": true,
									"h": true,
									"a": true,
									"o": false,
									"v": false,
									"d": true,
									"sm": "normal"
								}
							},
							{
								"uid": 74,
								"flags": {
									"x": true,
									"y": true,
									"z": true,
									"w": true,
									"h": true,
									"a": true,
									"o": false,
									"v": false,
									"d": true,
									"sm": "normal"
								}
							}
						],
						"flags": {
							"x": true,
							"y": true,
							"z": true,
							"w": true,
							"h": true,
							"a": true,
							"o": false,
							"v": false,
							"d": true,
							"sm": "normal"
						},
						"preview": {
							"transformX": 0,
							"transformY": 0,
							"transformZElevation": 0,
							"transformW": 0,
							"transformH": 0,
							"transformA": 0,
							"transformSX": 0,
							"transformSY": 0,
							"transformO": 0,
							"previewSceneGraph": false
						}
					},
					"instanceFolderItem": {
						"sid": 610675141839358,
						"expanded": true,
						"folderName": "",
						"indexInFolder": -1,
						"folderNestingLevel": -1
					},
					"showing": true,
					"locked": false,
					"world": {
						"x": 990,
						"y": 237,
						"width": 648,
						"height": 18,
						"originX": 1,
						"originY": 0.5,
						"color": [
							1,
							1,
							1,
							1
						],
						"angle": 0,
						"zElevation": 0
					}
				},
				{
					"type": "PlatLeft",
					"properties": {
						"left-margin": 18,
						"right-margin": 18,
						"top-margin": 18,
						"bottom-margin": 0,
						"edges": "tile",
						"fill": "tile",
						"initially-visible": true,
						"origin": "left",
						"seams": "overlap"
					},
					"uid": 7,
					"sid": 771737449048190,
					"tags": "",
					"instanceVariables": {},
					"behaviors": {
						"Tween": {
							"properties": {
								"enabled": true
							}
						},
						"Solid": {
							"properties": {
								"enabled": true,
								"tags": "geometry"
							}
						}
					},
					"sceneGraphData": {
						"parent-uid": null,
						"uid": 7,
						"children": [
							{
								"uid": 75,
								"flags": {
									"x": true,
									"y": true,
									"z": true,
									"w": true,
									"h": true,
									"a": true,
									"o": false,
									"v": false,
									"d": true,
									"sm": "normal"
								}
							}
						],
						"flags": {
							"x": true,
							"y": true,
							"z": true,
							"w": true,
							"h": true,
							"a": true,
							"o": false,
							"v": false,
							"d": true,
							"sm": "normal"
						},
						"preview": {
							"transformX": 0,
							"transformY": 0,
							"transformZElevation": 0,
							"transformW": 0,
							"transformH": 0,
							"transformA": 0,
							"transformSX": 0,
							"transformSY": 0,
							"transformO": 0,
							"previewSceneGraph": false
						}
					},
					"instanceFolderItem": {
						"sid": 771737449048190,
						"expanded": true,
						"folderName": "",
						"indexInFolder": -1,
						"folderNestingLevel": -1
					},
					"showing": true,
					"locked": false,
					"world": {
						"x": 288,
						"y": 123,
						"width": 648,
						"height": 18,
						"originX": 0,
						"originY": 0.5,
						"color": [
							1,
							1,
							1,
							1
						],
						"angle": 0,
						"zElevation": 0
					}
				},
				{
					"type": "Dragon",
					"properties": {
						"initially-visible": true,
						"initial-animation": "Idle",
						"initial-frame": 0,
						"enable-collisions": true,
						"live-preview": false
					},
					"uid": 24,
					"sid": 405825791692929,
					"tags": "",
					"instanceVariables": {
						"specialProbability": 1
					},
					"behaviors": {
						"Timer": {
							"properties": {}
						}
					},
					"sceneGraphData": {
						"parent-uid": null,
						"uid": 24,
						"children": [
							{
								"uid": 42,
								"flags": {
									"x": true,
									"y": true,
									"z": true,
									"w": true,
									"h": true,
									"a": true,
									"o": false,
									"v": false,
									"d": true,
									"sm": "normal"
								}
							},
							{
								"uid": 43,
								"flags": {
									"x": true,
									"y": true,
									"z": true,
									"w": true,
									"h": true,
									"a": true,
									"o": false,
									"v": false,
									"d": true,
									"sm": "normal"
								}
							}
						],
						"flags": {
							"x": true,
							"y": true,
							"z": true,
							"w": true,
							"h": true,
							"a": true,
							"o": false,
							"v": false,
							"d": true,
							"sm": "normal"
						},
						"preview": {
							"transformX": 0,
							"transformY": 0,
							"transformZElevation": 0,
							"transformW": 0,
							"transformH": 0,
							"transformA": 0,
							"transformSX": 0,
							"transformSY": 0,
							"transformO": 0,
							"previewSceneGraph": false
						}
					},
					"instanceFolderItem": {
						"sid": 405825791692929,
						"expanded": true,
						"folderName": "",
						"indexInFolder": -1,
						"folderNestingLevel": -1
					},
					"showing": true,
					"locked": false,
					"world": {
						"x": 576,
						"y": -94,
						"width": 156,
						"height": 117,
						"originX": 0.8012820512820513,
						"originY": 0.18803418803418803,
						"color": [
							1,
							1,
							1,
							1
						],
						"angle": 0,
						"zElevation": 0
					}
				},
				{
					"type": "LadderSpawner",
					"properties": {
						"initially-visible": false,
						"initial-animation": "Animation 1",
						"initial-frame": 0,
						"enable-collisions": true,
						"live-preview": false
					},
					"uid": 34,
					"sid": 501425025060077,
					"tags": "",
					"instanceVariables": {},
					"behaviors": {
						"LineOfSight": {
							"properties": {
								"obstacles": "solids",
								"range": 10000,
								"cone-of-view": 360,
								"use-collision-cells": true
							}
						},
						"Timer": {
							"properties": {}
						}
					},
					"sceneGraphData": {
						"parent-uid": 31,
						"uid": 34,
						"flags": {
							"x": true,
							"y": true,
							"z": true,
							"w": true,
							"h": true,
							"a": true,
							"o": false,
							"v": false,
							"d": true,
							"sm": "normal"
						},
						"preview": {
							"transformX": 0,
							"transformY": 0,
							"transformZElevation": 0,
							"transformW": 2.220446049250313e-16,
							"transformH": 2.220446049250313e-16,
							"transformA": 0,
							"transformSX": 0,
							"transformSY": 0,
							"transformO": 0,
							"previewSceneGraph": false
						}
					},
					"instanceFolderItem": {
						"sid": 501425025060077,
						"expanded": true,
						"folderName": "",
						"indexInFolder": -1,
						"folderNestingLevel": -1
					},
					"showing": true,
					"locked": false,
					"world": {
						"x": 774,
						"y": 579,
						"width": 24,
						"height": 24,
						"originX": 0.5,
						"originY": 0.5,
						"color": [
							1,
							1,
							1,
							1
						],
						"angle": 0,
						"zElevation": 0
					}
				},
				{
					"type": "LadderSpawner",
					"properties": {
						"initially-visible": false,
						"initial-animation": "Animation 1",
						"initial-frame": 0,
						"enable-collisions": true,
						"live-preview": false
					},
					"uid": 35,
					"sid": 686797973205132,
					"tags": "",
					"instanceVariables": {},
					"behaviors": {
						"LineOfSight": {
							"properties": {
								"obstacles": "solids",
								"range": 10000,
								"cone-of-view": 360,
								"use-collision-cells": true
							}
						},
						"Timer": {
							"properties": {}
						}
					},
					"sceneGraphData": {
						"parent-uid": 31,
						"uid": 35,
						"flags": {
							"x": true,
							"y": true,
							"z": true,
							"w": true,
							"h": true,
							"a": true,
							"o": false,
							"v": false,
							"d": true,
							"sm": "normal"
						},
						"preview": {
							"transformX": 0,
							"transformY": 0,
							"transformZElevation": 0,
							"transformW": 2.220446049250313e-16,
							"transformH": 2.220446049250313e-16,
							"transformA": 0,
							"transformSX": 0,
							"transformSY": 0,
							"transformO": 0,
							"previewSceneGraph": false
						}
					},
					"instanceFolderItem": {
						"sid": 686797973205132,
						"expanded": true,
						"folderName": "",
						"indexInFolder": -1,
						"folderNestingLevel": -1
					},
					"showing": true,
					"locked": false,
					"world": {
						"x": 540,
						"y": 579,
						"width": 24,
						"height": 24,
						"originX": 0.5,
						"originY": 0.5,
						"color": [
							1,
							1,
							1,
							1
						],
						"angle": 0,
						"zElevation": 0
					}
				},
				{
					"type": "LadderSpawner",
					"properties": {
						"initially-visible": false,
						"initial-animation": "Animation 1",
						"initial-frame": 0,
						"enable-collisions": true,
						"live-preview": false
					},
					"uid": 36,
					"sid": 953558149155462,
					"tags": "",
					"instanceVariables": {},
					"behaviors": {
						"LineOfSight": {
							"properties": {
								"obstacles": "solids",
								"range": 10000,
								"cone-of-view": 360,
								"use-collision-cells": true
							}
						},
						"Timer": {
							"properties": {}
						}
					},
					"sceneGraphData": {
						"parent-uid": 4,
						"uid": 36,
						"flags": {
							"x": true,
							"y": true,
							"z": true,
							"w": true,
							"h": true,
							"a": true,
							"o": false,
							"v": false,
							"d": true,
							"sm": "normal"
						},
						"preview": {
							"transformX": 0,
							"transformY": 0,
							"transformZElevation": 0,
							"transformW": 2.220446049250313e-16,
							"transformH": 2.220446049250313e-16,
							"transformA": 0,
							"transformSX": 0,
							"transformSY": 0,
							"transformO": 0,
							"previewSceneGraph": false
						}
					},
					"instanceFolderItem": {
						"sid": 953558149155462,
						"expanded": true,
						"folderName": "",
						"indexInFolder": -1,
						"folderNestingLevel": -1
					},
					"showing": true,
					"locked": false,
					"world": {
						"x": 666,
						"y": 465,
						"width": 24,
						"height": 24,
						"originX": 0.5,
						"originY": 0.5,
						"color": [
							1,
							1,
							1,
							1
						],
						"angle": 0,
						"zElevation": 0
					}
				},
				{
					"type": "LadderSpawner",
					"properties": {
						"initially-visible": false,
						"initial-animation": "Animation 1",
						"initial-frame": 0,
						"enable-collisions": true,
						"live-preview": false
					},
					"uid": 37,
					"sid": 786971516324281,
					"tags": "",
					"instanceVariables": {},
					"behaviors": {
						"LineOfSight": {
							"properties": {
								"obstacles": "solids",
								"range": 10000,
								"cone-of-view": 360,
								"use-collision-cells": true
							}
						},
						"Timer": {
							"properties": {}
						}
					},
					"sceneGraphData": {
						"parent-uid": 5,
						"uid": 37,
						"flags": {
							"x": true,
							"y": true,
							"z": true,
							"w": true,
							"h": true,
							"a": true,
							"o": false,
							"v": false,
							"d": true,
							"sm": "normal"
						},
						"preview": {
							"transformX": 0,
							"transformY": 0,
							"transformZElevation": 0,
							"transformW": 2.220446049250313e-16,
							"transformH": 2.220446049250313e-16,
							"transformA": 0,
							"transformSX": 0,
							"transformSY": 0,
							"transformO": 0,
							"previewSceneGraph": false
						}
					},
					"instanceFolderItem": {
						"sid": 786971516324281,
						"expanded": true,
						"folderName": "",
						"indexInFolder": -1,
						"folderNestingLevel": -1
					},
					"showing": true,
					"locked": false,
					"world": {
						"x": 558,
						"y": 351,
						"width": 24,
						"height": 24,
						"originX": 0.5,
						"originY": 0.5,
						"color": [
							1,
							1,
							1,
							1
						],
						"angle": 0,
						"zElevation": 0
					}
				},
				{
					"type": "LadderSpawner",
					"properties": {
						"initially-visible": false,
						"initial-animation": "Animation 1",
						"initial-frame": 0,
						"enable-collisions": true,
						"live-preview": false
					},
					"uid": 38,
					"sid": 508864574470694,
					"tags": "",
					"instanceVariables": {},
					"behaviors": {
						"LineOfSight": {
							"properties": {
								"obstacles": "solids",
								"range": 10000,
								"cone-of-view": 360,
								"use-collision-cells": true
							}
						},
						"Timer": {
							"properties": {}
						}
					},
					"sceneGraphData": {
						"parent-uid": 5,
						"uid": 38,
						"flags": {
							"x": true,
							"y": true,
							"z": true,
							"w": true,
							"h": true,
							"a": true,
							"o": false,
							"v": false,
							"d": true,
							"sm": "normal"
						},
						"preview": {
							"transformX": 0,
							"transformY": 0,
							"transformZElevation": 0,
							"transformW": 2.220446049250313e-16,
							"transformH": 2.220446049250313e-16,
							"transformA": 0,
							"transformSX": 0,
							"transformSY": 0,
							"transformO": 0,
							"previewSceneGraph": false
						}
					},
					"instanceFolderItem": {
						"sid": 508864574470694,
						"expanded": true,
						"folderName": "",
						"indexInFolder": -1,
						"folderNestingLevel": -1
					},
					"showing": true,
					"locked": false,
					"world": {
						"x": 792,
						"y": 351,
						"width": 24,
						"height": 24,
						"originX": 0.5,
						"originY": 0.5,
						"color": [
							1,
							1,
							1,
							1
						],
						"angle": 0,
						"zElevation": 0
					}
				},
				{
					"type": "LadderSpawner",
					"properties": {
						"initially-visible": false,
						"initial-animation": "Animation 1",
						"initial-frame": 0,
						"enable-collisions": true,
						"live-preview": false
					},
					"uid": 39,
					"sid": 619453745518295,
					"tags": "",
					"instanceVariables": {},
					"behaviors": {
						"LineOfSight": {
							"properties": {
								"obstacles": "solids",
								"range": 10000,
								"cone-of-view": 360,
								"use-collision-cells": true
							}
						},
						"Timer": {
							"properties": {}
						}
					},
					"sceneGraphData": {
						"parent-uid": 6,
						"uid": 39,
						"flags": {
							"x": true,
							"y": true,
							"z": true,
							"w": true,
							"h": true,
							"a": true,
							"o": false,
							"v": false,
							"d": true,
							"sm": "normal"
						},
						"preview": {
							"transformX": 0,
							"transformY": 0,
							"transformZElevation": 0,
							"transformW": 2.220446049250313e-16,
							"transformH": 2.220446049250313e-16,
							"transformA": 0,
							"transformSX": 0,
							"transformSY": 0,
							"transformO": 0,
							"previewSceneGraph": false
						}
					},
					"instanceFolderItem": {
						"sid": 619453745518295,
						"expanded": true,
						"folderName": "",
						"indexInFolder": -1,
						"folderNestingLevel": -1
					},
					"showing": true,
					"locked": false,
					"world": {
						"x": 468,
						"y": 237,
						"width": 24,
						"height": 24,
						"originX": 0.5,
						"originY": 0.5,
						"color": [
							1,
							1,
							1,
							1
						],
						"angle": 0,
						"zElevation": 0
					}
				},
				{
					"type": "WaterPickup",
					"properties": {
						"initially-visible": false,
						"origin": "top",
						"wrap-horizontal": "repeat",
						"wrap-vertical": "repeat",
						"image-offset-x": 0,
						"image-offset-y": 0,
						"image-scale-x": 1,
						"image-scale-y": 1,
						"image-angle": 0,
						"enable-tile-randomization": false,
						"x-random": 1,
						"y-random": 1,
						"angle-random": 1,
						"blend-margin-x": 0.1,
						"blend-margin-y": 0.1
					},
					"uid": 40,
					"sid": 154664828370446,
					"tags": "",
					"instanceVariables": {},
					"behaviors": {},
					"sceneGraphData": {
						"parent-uid": 62,
						"uid": 40,
						"flags": {
							"x": true,
							"y": true,
							"z": true,
							"w": false,
							"h": false,
							"a": false,
							"o": false,
							"v": false,
							"d": true,
							"sm": "normal"
						},
						"preview": {
							"transformX": 0,
							"transformY": 0,
							"transformZElevation": 0,
							"transformW": 2.220446049250313e-16,
							"transformH": 2.220446049250313e-16,
							"transformA": 0,
							"transformSX": 0,
							"transformSY": 0,
							"transformO": 0,
							"previewSceneGraph": false
						}
					},
					"instanceFolderItem": {
						"sid": 154664828370446,
						"expanded": true,
						"folderName": "",
						"indexInFolder": -1,
						"folderNestingLevel": -1
					},
					"showing": true,
					"locked": false,
					"world": {
						"x": 609.7709299168378,
						"y": 610.9362928440324,
						"width": 24,
						"height": 72,
						"originX": 0.5,
						"originY": 0,
						"color": [
							1,
							1,
							1,
							0.5
						],
						"angle": 0,
						"zElevation": 0
					}
				},
				{
					"type": "Collider",
					"properties": {
						"initially-visible": false,
						"origin": "top-left",
						"wrap-horizontal": "repeat",
						"wrap-vertical": "repeat",
						"image-offset-x": 0,
						"image-offset-y": 0,
						"image-scale-x": 1,
						"image-scale-y": 1,
						"image-angle": 0,
						"enable-tile-randomization": false,
						"x-random": 1,
						"y-random": 1,
						"angle-random": 1,
						"blend-margin-x": 0.1,
						"blend-margin-y": 0.1
					},
					"uid": 10,
					"sid": 602336826927383,
					"tags": "",
					"instanceVariables": {},
					"behaviors": {
						"Solid": {
							"properties": {
								"enabled": true,
								"tags": "geometry limit"
							}
						}
					},
					"instanceFolderItem": {
						"sid": 602336826927383,
						"expanded": true,
						"folderName": "",
						"indexInFolder": -1,
						"folderNestingLevel": -1
					},
					"showing": true,
					"locked": false,
					"world": {
						"x": 198,
						"y": 0,
						"width": 90,
						"height": 720,
						"originX": 0,
						"originY": 0,
						"color": [
							1,
							1,
							1,
							0.5
						],
						"angle": 0,
						"zElevation": 0
					}
				},
				{
					"type": "Collider",
					"properties": {
						"initially-visible": false,
						"origin": "top-left",
						"wrap-horizontal": "repeat",
						"wrap-vertical": "repeat",
						"image-offset-x": 0,
						"image-offset-y": 0,
						"image-scale-x": 1,
						"image-scale-y": 1,
						"image-angle": 0,
						"enable-tile-randomization": false,
						"x-random": 1,
						"y-random": 1,
						"angle-random": 1,
						"blend-margin-x": 0.1,
						"blend-margin-y": 0.1
					},
					"uid": 12,
					"sid": 682479262493788,
					"tags": "",
					"instanceVariables": {},
					"behaviors": {
						"Solid": {
							"properties": {
								"enabled": true,
								"tags": "geometry limit"
							}
						}
					},
					"instanceFolderItem": {
						"sid": 682479262493788,
						"expanded": true,
						"folderName": "",
						"indexInFolder": -1,
						"folderNestingLevel": -1
					},
					"showing": true,
					"locked": false,
					"world": {
						"x": 990,
						"y": 0,
						"width": 90,
						"height": 720,
						"originX": 0,
						"originY": 0,
						"color": [
							1,
							1,
							1,
							0.5
						],
						"angle": 0,
						"zElevation": 0
					}
				},
				{
					"type": "DragonRing",
					"properties": {
						"initially-visible": false,
						"initial-animation": "Intro",
						"initial-frame": 0,
						"enable-collisions": true,
						"live-preview": false
					},
					"uid": 42,
					"sid": 764760307577377,
					"tags": "",
					"instanceVariables": {},
					"behaviors": {},
					"sceneGraphData": {
						"parent-uid": 24,
						"uid": 42,
						"flags": {
							"x": true,
							"y": true,
							"z": true,
							"w": true,
							"h": true,
							"a": true,
							"o": false,
							"v": false,
							"d": true,
							"sm": "normal"
						},
						"preview": {
							"transformX": 0,
							"transformY": 0,
							"transformZElevation": 0,
							"transformW": 2.220446049250313e-16,
							"transformH": 2.220446049250313e-16,
							"transformA": 0,
							"transformSX": 0,
							"transformSY": 0,
							"transformO": 0,
							"previewSceneGraph": false
						}
					},
					"instanceFolderItem": {
						"sid": 764760307577377,
						"expanded": true,
						"folderName": "",
						"indexInFolder": -1,
						"folderNestingLevel": -1
					},
					"showing": true,
					"locked": false,
					"world": {
						"x": 666,
						"y": -180,
						"width": 320,
						"height": 320,
						"originX": 0.5,
						"originY": 0.5,
						"color": [
							1,
							1,
							1,
							1
						],
						"angle": 0,
						"zElevation": 0
					}
				},
				{
					"type": "DragonLoveParticles",
					"properties": {
						"rate": 0,
						"spray-cone": 0,
						"type": "continuous-spray",
						"object": -1,
						"initially-visible": true,
						"live-preview": false,
						"speed": 100,
						"size": 8,
						"opacity": 100,
						"grow-rate": 1,
						"x-randomiser": 72,
						"y-randomiser": 56,
						"initial-speed-randomiser": 0,
						"size-randomiser": 4,
						"grow-rate-randomiser": 0,
						"acceleration": 0,
						"gravity": 0,
						"angle-randomiser": 0,
						"life-speed-randomiser": 25,
						"opacity-randomiser": 0,
						"destroy-mode": "fade-to-invisible",
						"timeout": 2
					},
					"uid": 43,
					"sid": 627623572927601,
					"tags": "",
					"instanceVariables": {},
					"behaviors": {},
					"sceneGraphData": {
						"parent-uid": 24,
						"uid": 43,
						"flags": {
							"x": true,
							"y": true,
							"z": true,
							"w": true,
							"h": true,
							"a": true,
							"o": false,
							"v": false,
							"d": true,
							"sm": "normal"
						},
						"preview": {
							"transformX": 0,
							"transformY": 0,
							"transformZElevation": 0,
							"transformW": 2.220446049250313e-16,
							"transformH": 2.220446049250313e-16,
							"transformA": 0,
							"transformSX": 0,
							"transformSY": 0,
							"transformO": 0,
							"previewSceneGraph": false
						}
					},
					"instanceFolderItem": {
						"sid": 627623572927601,
						"expanded": true,
						"folderName": "",
						"indexInFolder": -1,
						"folderNestingLevel": -1
					},
					"showing": true,
					"locked": false,
					"world": {
						"x": 567,
						"y": -49,
						"width": 64,
						"height": 90,
						"originX": 0,
						"originY": 0.5,
						"color": [
							1,
							1,
							1,
							1
						],
						"angle": 4.71238898038469,
						"zElevation": 0
					}
				},
				{
					"type": "FlameLimit",
					"properties": {
						"initially-visible": false,
						"origin": "top-left",
						"wrap-horizontal": "repeat",
						"wrap-vertical": "repeat",
						"image-offset-x": 0,
						"image-offset-y": 0,
						"image-scale-x": 1,
						"image-scale-y": 1,
						"image-angle": 0,
						"enable-tile-randomization": false,
						"x-random": 1,
						"y-random": 1,
						"angle-random": 1,
						"blend-margin-x": 0.1,
						"blend-margin-y": 0.1
					},
					"uid": 48,
					"sid": 978660536251295,
					"tags": "",
					"instanceVariables": {},
					"behaviors": {},
					"instanceFolderItem": {
						"sid": 978660536251295,
						"expanded": true,
						"folderName": "",
						"indexInFolder": -1,
						"folderNestingLevel": -1
					},
					"showing": true,
					"locked": false,
					"world": {
						"x": 288,
						"y": 0,
						"width": 18,
						"height": 576,
						"originX": 0,
						"originY": 0,
						"color": [
							1,
							1,
							1,
							0.5
						],
						"angle": 0,
						"zElevation": 0
					}
				},
				{
					"type": "FlameLimit",
					"properties": {
						"initially-visible": false,
						"origin": "top-left",
						"wrap-horizontal": "repeat",
						"wrap-vertical": "repeat",
						"image-offset-x": 0,
						"image-offset-y": 0,
						"image-scale-x": 1,
						"image-scale-y": 1,
						"image-angle": 0,
						"enable-tile-randomization": false,
						"x-random": 1,
						"y-random": 1,
						"angle-random": 1,
						"blend-margin-x": 0.1,
						"blend-margin-y": 0.1
					},
					"uid": 49,
					"sid": 175877187245485,
					"tags": "",
					"instanceVariables": {},
					"behaviors": {},
					"instanceFolderItem": {
						"sid": 175877187245485,
						"expanded": true,
						"folderName": "",
						"indexInFolder": -1,
						"folderNestingLevel": -1
					},
					"showing": true,
					"locked": false,
					"world": {
						"x": 972,
						"y": 0,
						"width": 18,
						"height": 720,
						"originX": 0,
						"originY": 0,
						"color": [
							1,
							1,
							1,
							0.5
						],
						"angle": 0,
						"zElevation": 0
					}
				},
				{
					"type": "FlameSummonSpot",
					"properties": {
						"initially-visible": false,
						"initial-animation": "Animation 1",
						"initial-frame": 0,
						"enable-collisions": true,
						"live-preview": false
					},
					"uid": 46,
					"sid": 554831287307773,
					"tags": "",
					"instanceVariables": {},
					"behaviors": {},
					"sceneGraphData": {
						"parent-uid": 31,
						"uid": 46,
						"flags": {
							"x": true,
							"y": true,
							"z": true,
							"w": true,
							"h": true,
							"a": true,
							"o": false,
							"v": false,
							"d": true,
							"sm": "normal"
						},
						"preview": {
							"transformX": 0,
							"transformY": 0,
							"transformZElevation": 0,
							"transformW": 2.220446049250313e-16,
							"transformH": 2.220446049250313e-16,
							"transformA": 0,
							"transformSX": 0,
							"transformSY": 0,
							"transformO": 0,
							"previewSceneGraph": false
						}
					},
					"instanceFolderItem": {
						"sid": 554831287307773,
						"expanded": true,
						"folderName": "",
						"indexInFolder": -1,
						"folderNestingLevel": -1
					},
					"showing": true,
					"locked": false,
					"world": {
						"x": 720,
						"y": 554,
						"width": 32,
						"height": 32,
						"originX": 0.5,
						"originY": 0.5,
						"color": [
							1,
							1,
							1,
							1
						],
						"angle": 0,
						"zElevation": 0
					}
				},
				{
					"type": "FlameSummonSpot",
					"properties": {
						"initially-visible": false,
						"initial-animation": "Animation 1",
						"initial-frame": 0,
						"enable-collisions": true,
						"live-preview": false
					},
					"uid": 50,
					"sid": 744415994691544,
					"tags": "",
					"instanceVariables": {},
					"behaviors": {},
					"sceneGraphData": {
						"parent-uid": 4,
						"uid": 50,
						"flags": {
							"x": true,
							"y": true,
							"z": true,
							"w": true,
							"h": true,
							"a": true,
							"o": false,
							"v": false,
							"d": true,
							"sm": "normal"
						},
						"preview": {
							"transformX": 0,
							"transformY": 0,
							"transformZElevation": 0,
							"transformW": 2.220446049250313e-16,
							"transformH": 2.220446049250313e-16,
							"transformA": 0,
							"transformSX": 0,
							"transformSY": 0,
							"transformO": 0,
							"previewSceneGraph": false
						}
					},
					"instanceFolderItem": {
						"sid": 744415994691544,
						"expanded": true,
						"folderName": "",
						"indexInFolder": -1,
						"folderNestingLevel": -1
					},
					"showing": true,
					"locked": false,
					"world": {
						"x": 720,
						"y": 440,
						"width": 32,
						"height": 32,
						"originX": 0.5,
						"originY": 0.5,
						"color": [
							1,
							1,
							1,
							1
						],
						"angle": 0,
						"zElevation": 0
					}
				},
				{
					"type": "FlameSummonSpot",
					"properties": {
						"initially-visible": false,
						"initial-animation": "Animation 1",
						"initial-frame": 0,
						"enable-collisions": true,
						"live-preview": false
					},
					"uid": 51,
					"sid": 477996572702876,
					"tags": "",
					"instanceVariables": {},
					"behaviors": {},
					"sceneGraphData": {
						"parent-uid": 5,
						"uid": 51,
						"flags": {
							"x": true,
							"y": true,
							"z": true,
							"w": true,
							"h": true,
							"a": true,
							"o": false,
							"v": false,
							"d": true,
							"sm": "normal"
						},
						"preview": {
							"transformX": 0,
							"transformY": 0,
							"transformZElevation": 0,
							"transformW": 2.220446049250313e-16,
							"transformH": 2.220446049250313e-16,
							"transformA": 0,
							"transformSX": 0,
							"transformSY": 0,
							"transformO": 0,
							"previewSceneGraph": false
						}
					},
					"instanceFolderItem": {
						"sid": 477996572702876,
						"expanded": true,
						"folderName": "",
						"indexInFolder": -1,
						"folderNestingLevel": -1
					},
					"showing": true,
					"locked": false,
					"world": {
						"x": 720,
						"y": 326,
						"width": 32,
						"height": 32,
						"originX": 0.5,
						"originY": 0.5,
						"color": [
							1,
							1,
							1,
							1
						],
						"angle": 0,
						"zElevation": 0
					}
				},
				{
					"type": "FlameSummonSpot",
					"properties": {
						"initially-visible": false,
						"initial-animation": "Animation 1",
						"initial-frame": 0,
						"enable-collisions": true,
						"live-preview": false
					},
					"uid": 52,
					"sid": 873688690620739,
					"tags": "",
					"instanceVariables": {},
					"behaviors": {},
					"sceneGraphData": {
						"parent-uid": 6,
						"uid": 52,
						"flags": {
							"x": true,
							"y": true,
							"z": true,
							"w": true,
							"h": true,
							"a": true,
							"o": false,
							"v": false,
							"d": true,
							"sm": "normal"
						},
						"preview": {
							"transformX": 0,
							"transformY": 0,
							"transformZElevation": 0,
							"transformW": 2.220446049250313e-16,
							"transformH": 2.220446049250313e-16,
							"transformA": 0,
							"transformSX": 0,
							"transformSY": 0,
							"transformO": 0,
							"previewSceneGraph": false
						}
					},
					"instanceFolderItem": {
						"sid": 873688690620739,
						"expanded": true,
						"folderName": "",
						"indexInFolder": -1,
						"folderNestingLevel": -1
					},
					"showing": true,
					"locked": false,
					"world": {
						"x": 720,
						"y": 212,
						"width": 32,
						"height": 32,
						"originX": 0.5,
						"originY": 0.5,
						"color": [
							1,
							1,
							1,
							1
						],
						"angle": 0,
						"zElevation": 0
					}
				},
				{
					"type": "WinZone",
					"properties": {
						"initially-visible": false,
						"origin": "top-left",
						"wrap-horizontal": "repeat",
						"wrap-vertical": "repeat",
						"image-offset-x": 0,
						"image-offset-y": 0,
						"image-scale-x": 1,
						"image-scale-y": 1,
						"image-angle": 0,
						"enable-tile-randomization": false,
						"x-random": 1,
						"y-random": 1,
						"angle-random": 1,
						"blend-margin-x": 0.1,
						"blend-margin-y": 0.1
					},
					"uid": 55,
					"sid": 152203742330826,
					"tags": "",
					"instanceVariables": {},
					"behaviors": {},
					"instanceFolderItem": {
						"sid": 152203742330826,
						"expanded": true,
						"folderName": "",
						"indexInFolder": -1,
						"folderNestingLevel": -1
					},
					"showing": true,
					"locked": false,
					"world": {
						"x": 766,
						"y": -75,
						"width": 36,
						"height": 216,
						"originX": 0,
						"originY": 0,
						"color": [
							1,
							1,
							1,
							0.25
						],
						"angle": 0,
						"zElevation": 0
					}
				},
				{
					"type": "Mountain1",
					"properties": {
						"initially-visible": true,
						"initial-animation": "Animation 1",
						"initial-frame": 0,
						"enable-collisions": true,
						"live-preview": false
					},
					"uid": 3,
					"sid": 196846406617588,
					"tags": "",
					"instanceVariables": {},
					"behaviors": {},
					"instanceFolderItem": {
						"sid": 196846406617588,
						"expanded": true,
						"folderName": "",
						"indexInFolder": -1,
						"folderNestingLevel": -1
					},
					"showing": true,
					"locked": false,
					"world": {
						"x": 1134,
						"y": 295,
						"width": 466,
						"height": 532,
						"originX": 0.5,
						"originY": 0.5,
						"color": [
							1,
							1,
							1,
							1
						],
						"angle": 0,
						"zElevation": 0
					}
				},
				{
					"type": "Mountain2",
					"properties": {
						"initially-visible": true,
						"initial-animation": "Animation 1",
						"initial-frame": 0,
						"enable-collisions": true,
						"live-preview": false
					},
					"uid": 13,
					"sid": 661968391068112,
					"tags": "",
					"instanceVariables": {},
					"behaviors": {},
					"instanceFolderItem": {
						"sid": 661968391068112,
						"expanded": true,
						"folderName": "",
						"indexInFolder": -1,
						"folderNestingLevel": -1
					},
					"showing": true,
					"locked": false,
					"world": {
						"x": 64,
						"y": 525,
						"width": 466,
						"height": 532,
						"originX": 0.5,
						"originY": 0.5,
						"color": [
							1,
							1,
							1,
							1
						],
						"angle": 0,
						"zElevation": 0
					}
				},
				{
					"type": "Tree",
					"properties": {
						"initially-visible": true,
						"initial-animation": "Animation 1",
						"initial-frame": 0,
						"enable-collisions": true,
						"live-preview": false
					},
					"uid": 21,
					"sid": 860078285226138,
					"tags": "",
					"instanceVariables": {},
					"behaviors": {},
					"instanceFolderItem": {
						"sid": 860078285226138,
						"expanded": true,
						"folderName": "",
						"indexInFolder": -1,
						"folderNestingLevel": -1
					},
					"showing": true,
					"locked": false,
					"world": {
						"x": 1152,
						"y": 306,
						"width": 466,
						"height": 532,
						"originX": 0.5,
						"originY": 0.5,
						"color": [
							1,
							1,
							1,
							1
						],
						"angle": 0,
						"zElevation": 0
					}
				},
				{
					"type": "Sign1",
					"properties": {
						"initially-visible": true,
						"initial-animation": "Animation 1",
						"initial-frame": 0,
						"enable-collisions": true,
						"live-preview": false
					},
					"uid": 20,
					"sid": 677598400630652,
					"tags": "",
					"instanceVariables": {},
					"behaviors": {},
					"instanceFolderItem": {
						"sid": 677598400630652,
						"expanded": true,
						"folderName": "",
						"indexInFolder": -1,
						"folderNestingLevel": -1
					},
					"showing": true,
					"locked": false,
					"world": {
						"x": 72,
						"y": 562,
						"width": 112,
						"height": 80,
						"originX": 0.5,
						"originY": 0.5,
						"color": [
							1,
							1,
							1,
							1
						],
						"angle": 0,
						"zElevation": 0
					}
				},
				{
					"type": "Sign2",
					"properties": {
						"initially-visible": true,
						"initial-animation": "Animation 1",
						"initial-frame": 0,
						"enable-collisions": true,
						"live-preview": false
					},
					"uid": 61,
					"sid": 708659055915916,
					"tags": "",
					"instanceVariables": {},
					"behaviors": {},
					"instanceFolderItem": {
						"sid": 708659055915916,
						"expanded": true,
						"folderName": "",
						"indexInFolder": -1,
						"folderNestingLevel": -1
					},
					"showing": true,
					"locked": false,
					"world": {
						"x": 1152,
						"y": 281,
						"width": 73,
						"height": 44,
						"originX": 0.5,
						"originY": 0.5,
						"color": [
							1,
							1,
							1,
							1
						],
						"angle": 0,
						"zElevation": 0
					}
				},
				{
					"type": "Stalactite",
					"properties": {
						"initially-visible": true,
						"initial-animation": "Animation 1",
						"initial-frame": 0,
						"enable-collisions": true,
						"live-preview": false
					},
					"uid": 62,
					"sid": 916339079437809,
					"tags": "",
					"instanceVariables": {},
					"behaviors": {},
					"sceneGraphData": {
						"parent-uid": 31,
						"uid": 62,
						"children": [
							{
								"uid": 40,
								"flags": {
									"x": true,
									"y": true,
									"z": true,
									"w": false,
									"h": false,
									"a": false,
									"o": false,
									"v": false,
									"d": true,
									"sm": "normal"
								}
							}
						],
						"flags": {
							"x": true,
							"y": true,
							"z": true,
							"w": true,
							"h": true,
							"a": true,
							"o": false,
							"v": false,
							"d": true,
							"sm": "normal"
						},
						"preview": {
							"transformX": 0,
							"transformY": 0,
							"transformZElevation": 0,
							"transformW": 2.220446049250313e-16,
							"transformH": 2.220446049250313e-16,
							"transformA": 0,
							"transformSX": 0,
							"transformSY": 0,
							"transformO": 0,
							"previewSceneGraph": false
						}
					},
					"instanceFolderItem": {
						"sid": 916339079437809,
						"expanded": true,
						"folderName": "",
						"indexInFolder": -1,
						"folderNestingLevel": -1
					},
					"showing": true,
					"locked": false,
					"world": {
						"x": 612,
						"y": 594,
						"width": 38,
						"height": 50,
						"originX": 0.5,
						"originY": 0.5,
						"color": [
							1,
							1,
							1,
							1
						],
						"angle": 0,
						"zElevation": 0
					}
				},
				{
					"type": "PlayerSprite",
					"properties": {
						"initially-visible": true,
						"initial-animation": "E_Idle",
						"initial-frame": 0,
						"enable-collisions": true,
						"live-preview": false
					},
					"uid": 11,
					"sid": 578120506312140,
					"tags": "",
					"instanceVariables": {},
					"behaviors": {},
					"sceneGraphData": {
						"parent-uid": 2,
						"uid": 11,
						"flags": {
							"x": true,
							"y": true,
							"z": false,
							"w": true,
							"h": false,
							"a": false,
							"o": false,
							"v": false,
							"d": true,
							"sm": "normal"
						},
						"preview": {
							"transformX": 0,
							"transformY": 0,
							"transformZElevation": 0,
							"transformW": 0,
							"transformH": 0,
							"transformA": 0,
							"transformSX": 0,
							"transformSY": 0,
							"transformO": 0,
							"previewSceneGraph": false
						}
					},
					"instanceFolderItem": {
						"sid": 578120506312140,
						"expanded": true,
						"folderName": "",
						"indexInFolder": -1,
						"folderNestingLevel": -1
					},
					"showing": true,
					"locked": false,
					"world": {
						"x": 432,
						"y": 687,
						"width": 38,
						"height": 50,
						"originX": 0.5,
						"originY": 0.9800000000000001,
						"color": [
							1,
							1,
							1,
							1
						],
						"angle": 0,
						"zElevation": 0
					}
				},
				{
					"type": "Stalactite",
					"properties": {
						"initially-visible": true,
						"initial-animation": "Animation 3",
						"initial-frame": 0,
						"enable-collisions": true,
						"live-preview": false
					},
					"uid": 70,
					"sid": 562026030773931,
					"tags": "",
					"instanceVariables": {},
					"behaviors": {},
					"sceneGraphData": {
						"parent-uid": 4,
						"uid": 70,
						"children": [
							{
								"uid": 77,
								"flags": {
									"x": true,
									"y": true,
									"z": true,
									"w": false,
									"h": false,
									"a": false,
									"o": false,
									"v": false,
									"d": true,
									"sm": "normal"
								}
							}
						],
						"flags": {
							"x": true,
							"y": true,
							"z": true,
							"w": true,
							"h": true,
							"a": true,
							"o": false,
							"v": false,
							"d": true,
							"sm": "normal"
						},
						"preview": {
							"transformX": 0,
							"transformY": 0,
							"transformZElevation": 0,
							"transformW": 2.220446049250313e-16,
							"transformH": 2.220446049250313e-16,
							"transformA": 0,
							"transformSX": 0,
							"transformSY": 0,
							"transformO": 0,
							"previewSceneGraph": false
						}
					},
					"instanceFolderItem": {
						"sid": 562026030773931,
						"expanded": true,
						"folderName": "",
						"indexInFolder": -1,
						"folderNestingLevel": -1
					},
					"showing": true,
					"locked": false,
					"world": {
						"x": 881,
						"y": 479,
						"width": 38,
						"height": 50,
						"originX": 0.5,
						"originY": 0.5,
						"color": [
							1,
							1,
							1,
							1
						],
						"angle": 0,
						"zElevation": 0
					}
				},
				{
					"type": "Stalactite",
					"properties": {
						"initially-visible": true,
						"initial-animation": "Animation 2",
						"initial-frame": 0,
						"enable-collisions": true,
						"live-preview": false
					},
					"uid": 71,
					"sid": 438847758150070,
					"tags": "",
					"instanceVariables": {},
					"behaviors": {},
					"sceneGraphData": {
						"parent-uid": 4,
						"uid": 71,
						"children": [
							{
								"uid": 41,
								"flags": {
									"x": true,
									"y": true,
									"z": true,
									"w": false,
									"h": false,
									"a": false,
									"o": false,
									"v": false,
									"d": true,
									"sm": "normal"
								}
							}
						],
						"flags": {
							"x": true,
							"y": true,
							"z": true,
							"w": true,
							"h": true,
							"a": true,
							"o": false,
							"v": false,
							"d": true,
							"sm": "normal"
						},
						"preview": {
							"transformX": 0,
							"transformY": 0,
							"transformZElevation": 0,
							"transformW": 2.220446049250313e-16,
							"transformH": 2.220446049250313e-16,
							"transformA": 0,
							"transformSX": 0,
							"transformSY": 0,
							"transformO": 0,
							"previewSceneGraph": false
						}
					},
					"instanceFolderItem": {
						"sid": 438847758150070,
						"expanded": true,
						"folderName": "",
						"indexInFolder": -1,
						"folderNestingLevel": -1
					},
					"showing": true,
					"locked": false,
					"world": {
						"x": 451,
						"y": 480,
						"width": 38,
						"height": 50,
						"originX": 0.5,
						"originY": 0.5,
						"color": [
							1,
							1,
							1,
							1
						],
						"angle": 0,
						"zElevation": 0
					}
				},
				{
					"type": "Stalactite",
					"properties": {
						"initially-visible": true,
						"initial-animation": "Animation 2",
						"initial-frame": 0,
						"enable-collisions": true,
						"live-preview": false
					},
					"uid": 72,
					"sid": 749640733419649,
					"tags": "",
					"instanceVariables": {},
					"behaviors": {},
					"sceneGraphData": {
						"parent-uid": 5,
						"uid": 72,
						"children": [
							{
								"uid": 79,
								"flags": {
									"x": true,
									"y": true,
									"z": true,
									"w": false,
									"h": false,
									"a": false,
									"o": false,
									"v": false,
									"d": true,
									"sm": "normal"
								}
							}
						],
						"flags": {
							"x": true,
							"y": true,
							"z": true,
							"w": true,
							"h": true,
							"a": true,
							"o": false,
							"v": false,
							"d": true,
							"sm": "normal"
						},
						"preview": {
							"transformX": 0,
							"transformY": 0,
							"transformZElevation": 0,
							"transformW": 2.220446049250313e-16,
							"transformH": 2.220446049250313e-16,
							"transformA": 0,
							"transformSX": 0,
							"transformSY": 0,
							"transformO": 0,
							"previewSceneGraph": false
						}
					},
					"instanceFolderItem": {
						"sid": 749640733419649,
						"expanded": true,
						"folderName": "",
						"indexInFolder": -1,
						"folderNestingLevel": -1
					},
					"showing": true,
					"locked": false,
					"world": {
						"x": 594,
						"y": 365,
						"width": 38,
						"height": 50,
						"originX": 0.5,
						"originY": 0.5,
						"color": [
							1,
							1,
							1,
							1
						],
						"angle": 0,
						"zElevation": 0
					}
				},
				{
					"type": "Stalactite",
					"properties": {
						"initially-visible": true,
						"initial-animation": "Animation 1",
						"initial-frame": 0,
						"enable-collisions": true,
						"live-preview": false
					},
					"uid": 73,
					"sid": 873051869045968,
					"tags": "",
					"instanceVariables": {},
					"behaviors": {},
					"sceneGraphData": {
						"parent-uid": 5,
						"uid": 73,
						"children": [
							{
								"uid": 78,
								"flags": {
									"x": true,
									"y": true,
									"z": true,
									"w": false,
									"h": false,
									"a": false,
									"o": false,
									"v": false,
									"d": true,
									"sm": "normal"
								}
							}
						],
						"flags": {
							"x": true,
							"y": true,
							"z": true,
							"w": true,
							"h": true,
							"a": true,
							"o": false,
							"v": false,
							"d": true,
							"sm": "normal"
						},
						"preview": {
							"transformX": 0,
							"transformY": 0,
							"transformZElevation": 0,
							"transformW": 2.220446049250313e-16,
							"transformH": 2.220446049250313e-16,
							"transformA": 0,
							"transformSX": 0,
							"transformSY": 0,
							"transformO": 0,
							"previewSceneGraph": false
						}
					},
					"instanceFolderItem": {
						"sid": 873051869045968,
						"expanded": true,
						"folderName": "",
						"indexInFolder": -1,
						"folderNestingLevel": -1
					},
					"showing": true,
					"locked": false,
					"world": {
						"x": 877,
						"y": 366,
						"width": 38,
						"height": 50,
						"originX": 0.5,
						"originY": 0.5,
						"color": [
							1,
							1,
							1,
							1
						],
						"angle": 0,
						"zElevation": 0
					}
				},
				{
					"type": "Stalactite",
					"properties": {
						"initially-visible": true,
						"initial-animation": "Animation 3",
						"initial-frame": 0,
						"enable-collisions": true,
						"live-preview": false
					},
					"uid": 74,
					"sid": 981463602976090,
					"tags": "",
					"instanceVariables": {},
					"behaviors": {},
					"sceneGraphData": {
						"parent-uid": 6,
						"uid": 74,
						"children": [
							{
								"uid": 80,
								"flags": {
									"x": true,
									"y": true,
									"z": true,
									"w": false,
									"h": false,
									"a": false,
									"o": false,
									"v": false,
									"d": true,
									"sm": "normal"
								}
							}
						],
						"flags": {
							"x": true,
							"y": true,
							"z": true,
							"w": true,
							"h": true,
							"a": true,
							"o": false,
							"v": false,
							"d": true,
							"sm": "normal"
						},
						"preview": {
							"transformX": 0,
							"transformY": 0,
							"transformZElevation": 0,
							"transformW": 2.220446049250313e-16,
							"transformH": 2.220446049250313e-16,
							"transformA": 0,
							"transformSX": 0,
							"transformSY": 0,
							"transformO": 0,
							"previewSceneGraph": false
						}
					},
					"instanceFolderItem": {
						"sid": 981463602976090,
						"expanded": true,
						"folderName": "",
						"indexInFolder": -1,
						"folderNestingLevel": -1
					},
					"showing": true,
					"locked": false,
					"world": {
						"x": 746,
						"y": 251,
						"width": 38,
						"height": 50,
						"originX": 0.5,
						"originY": 0.5,
						"color": [
							1,
							1,
							1,
							1
						],
						"angle": 0,
						"zElevation": 0
					}
				},
				{
					"type": "Stalactite",
					"properties": {
						"initially-visible": true,
						"initial-animation": "Animation 1",
						"initial-frame": 0,
						"enable-collisions": true,
						"live-preview": false
					},
					"uid": 75,
					"sid": 533999599489356,
					"tags": "",
					"instanceVariables": {},
					"behaviors": {},
					"sceneGraphData": {
						"parent-uid": 7,
						"uid": 75,
						"children": [
							{
								"uid": 81,
								"flags": {
									"x": true,
									"y": true,
									"z": true,
									"w": false,
									"h": false,
									"a": false,
									"o": false,
									"v": false,
									"d": true,
									"sm": "normal"
								}
							}
						],
						"flags": {
							"x": true,
							"y": true,
							"z": true,
							"w": true,
							"h": true,
							"a": true,
							"o": false,
							"v": false,
							"d": true,
							"sm": "normal"
						},
						"preview": {
							"transformX": 0,
							"transformY": 0,
							"transformZElevation": 0,
							"transformW": 2.220446049250313e-16,
							"transformH": 2.220446049250313e-16,
							"transformA": 0,
							"transformSX": 0,
							"transformSY": 0,
							"transformO": 0,
							"previewSceneGraph": false
						}
					},
					"instanceFolderItem": {
						"sid": 533999599489356,
						"expanded": true,
						"folderName": "",
						"indexInFolder": -1,
						"folderNestingLevel": -1
					},
					"showing": true,
					"locked": false,
					"world": {
						"x": 445,
						"y": 137,
						"width": 38,
						"height": 50,
						"originX": 0.5,
						"originY": 0.5,
						"color": [
							1,
							1,
							1,
							1
						],
						"angle": 0,
						"zElevation": 0
					}
				},
				{
					"type": "WaterPickup",
					"properties": {
						"initially-visible": false,
						"origin": "top",
						"wrap-horizontal": "repeat",
						"wrap-vertical": "repeat",
						"image-offset-x": 0,
						"image-offset-y": 0,
						"image-scale-x": 1,
						"image-scale-y": 1,
						"image-angle": 0,
						"enable-tile-randomization": false,
						"x-random": 1,
						"y-random": 1,
						"angle-random": 1,
						"blend-margin-x": 0.1,
						"blend-margin-y": 0.1
					},
					"uid": 41,
					"sid": 927108998548124,
					"tags": "",
					"instanceVariables": {},
					"behaviors": {},
					"sceneGraphData": {
						"parent-uid": 71,
						"uid": 41,
						"flags": {
							"x": true,
							"y": true,
							"z": true,
							"w": false,
							"h": false,
							"a": false,
							"o": false,
							"v": false,
							"d": true,
							"sm": "normal"
						},
						"preview": {
							"transformX": 0,
							"transformY": 0,
							"transformZElevation": 0,
							"transformW": 2.220446049250313e-16,
							"transformH": 2.220446049250313e-16,
							"transformA": 0,
							"transformSX": 0,
							"transformSY": 0,
							"transformO": 0,
							"previewSceneGraph": false
						}
					},
					"instanceFolderItem": {
						"sid": 927108998548124,
						"expanded": true,
						"folderName": "",
						"indexInFolder": -1,
						"folderNestingLevel": -1
					},
					"showing": true,
					"locked": false,
					"world": {
						"x": 451.5237201109288,
						"y": 508.18852343626554,
						"width": 24,
						"height": 72,
						"originX": 0.5,
						"originY": 0,
						"color": [
							1,
							1,
							1,
							0.5
						],
						"angle": 0,
						"zElevation": 0
					}
				},
				{
					"type": "WaterPickup",
					"properties": {
						"initially-visible": false,
						"origin": "top",
						"wrap-horizontal": "repeat",
						"wrap-vertical": "repeat",
						"image-offset-x": 0,
						"image-offset-y": 0,
						"image-scale-x": 1,
						"image-scale-y": 1,
						"image-angle": 0,
						"enable-tile-randomization": false,
						"x-random": 1,
						"y-random": 1,
						"angle-random": 1,
						"blend-margin-x": 0.1,
						"blend-margin-y": 0.1
					},
					"uid": 77,
					"sid": 107162540697888,
					"tags": "",
					"instanceVariables": {},
					"behaviors": {},
					"sceneGraphData": {
						"parent-uid": 70,
						"uid": 77,
						"flags": {
							"x": true,
							"y": true,
							"z": true,
							"w": false,
							"h": false,
							"a": false,
							"o": false,
							"v": false,
							"d": true,
							"sm": "normal"
						},
						"preview": {
							"transformX": 0,
							"transformY": 0,
							"transformZElevation": 0,
							"transformW": 2.220446049250313e-16,
							"transformH": 2.220446049250313e-16,
							"transformA": 0,
							"transformSX": 0,
							"transformSY": 0,
							"transformO": 0,
							"previewSceneGraph": false
						}
					},
					"instanceFolderItem": {
						"sid": 107162540697888,
						"expanded": true,
						"folderName": "",
						"indexInFolder": -1,
						"folderNestingLevel": -1
					},
					"showing": true,
					"locked": false,
					"world": {
						"x": 879.8820840991526,
						"y": 493.685432717045,
						"width": 24,
						"height": 108,
						"originX": 0.5,
						"originY": 0,
						"color": [
							1,
							1,
							1,
							0.5
						],
						"angle": 0,
						"zElevation": 0
					}
				},
				{
					"type": "WaterPickup",
					"properties": {
						"initially-visible": false,
						"origin": "top",
						"wrap-horizontal": "repeat",
						"wrap-vertical": "repeat",
						"image-offset-x": 0,
						"image-offset-y": 0,
						"image-scale-x": 1,
						"image-scale-y": 1,
						"image-angle": 0,
						"enable-tile-randomization": false,
						"x-random": 1,
						"y-random": 1,
						"angle-random": 1,
						"blend-margin-x": 0.1,
						"blend-margin-y": 0.1
					},
					"uid": 78,
					"sid": 891265440419019,
					"tags": "",
					"instanceVariables": {},
					"behaviors": {},
					"sceneGraphData": {
						"parent-uid": 73,
						"uid": 78,
						"flags": {
							"x": true,
							"y": true,
							"z": true,
							"w": false,
							"h": false,
							"a": false,
							"o": false,
							"v": false,
							"d": true,
							"sm": "normal"
						},
						"preview": {
							"transformX": 0,
							"transformY": 0,
							"transformZElevation": 0,
							"transformW": 2.220446049250313e-16,
							"transformH": 2.220446049250313e-16,
							"transformA": 0,
							"transformSX": 0,
							"transformSY": 0,
							"transformO": 0,
							"previewSceneGraph": false
						}
					},
					"instanceFolderItem": {
						"sid": 891265440419019,
						"expanded": true,
						"folderName": "",
						"indexInFolder": -1,
						"folderNestingLevel": -1
					},
					"showing": true,
					"locked": false,
					"world": {
						"x": 873.4077566267998,
						"y": 388.8053212484125,
						"width": 24,
						"height": 72,
						"originX": 0.5,
						"originY": 0,
						"color": [
							1,
							1,
							1,
							0.5
						],
						"angle": 0,
						"zElevation": 0
					}
				},
				{
					"type": "WaterPickup",
					"properties": {
						"initially-visible": false,
						"origin": "top",
						"wrap-horizontal": "repeat",
						"wrap-vertical": "repeat",
						"image-offset-x": 0,
						"image-offset-y": 0,
						"image-scale-x": 1,
						"image-scale-y": 1,
						"image-angle": 0,
						"enable-tile-randomization": false,
						"x-random": 1,
						"y-random": 1,
						"angle-random": 1,
						"blend-margin-x": 0.1,
						"blend-margin-y": 0.1
					},
					"uid": 79,
					"sid": 705714706247349,
					"tags": "",
					"instanceVariables": {},
					"behaviors": {},
					"sceneGraphData": {
						"parent-uid": 72,
						"uid": 79,
						"flags": {
							"x": true,
							"y": true,
							"z": true,
							"w": false,
							"h": false,
							"a": false,
							"o": false,
							"v": false,
							"d": true,
							"sm": "normal"
						},
						"preview": {
							"transformX": 0,
							"transformY": 0,
							"transformZElevation": 0,
							"transformW": 2.220446049250313e-16,
							"transformH": 2.220446049250313e-16,
							"transformA": 0,
							"transformSX": 0,
							"transformSY": 0,
							"transformO": 0,
							"previewSceneGraph": false
						}
					},
					"instanceFolderItem": {
						"sid": 705714706247349,
						"expanded": true,
						"folderName": "",
						"indexInFolder": -1,
						"folderNestingLevel": -1
					},
					"showing": true,
					"locked": false,
					"world": {
						"x": 590.8479342474984,
						"y": 382.9956160969048,
						"width": 24,
						"height": 72,
						"originX": 0.5,
						"originY": 0,
						"color": [
							1,
							1,
							1,
							0.5
						],
						"angle": 0,
						"zElevation": 0
					}
				},
				{
					"type": "WaterPickup",
					"properties": {
						"initially-visible": false,
						"origin": "top",
						"wrap-horizontal": "repeat",
						"wrap-vertical": "repeat",
						"image-offset-x": 0,
						"image-offset-y": 0,
						"image-scale-x": 1,
						"image-scale-y": 1,
						"image-angle": 0,
						"enable-tile-randomization": false,
						"x-random": 1,
						"y-random": 1,
						"angle-random": 1,
						"blend-margin-x": 0.1,
						"blend-margin-y": 0.1
					},
					"uid": 80,
					"sid": 777789192023907,
					"tags": "",
					"instanceVariables": {},
					"behaviors": {},
					"sceneGraphData": {
						"parent-uid": 74,
						"uid": 80,
						"flags": {
							"x": true,
							"y": true,
							"z": true,
							"w": false,
							"h": false,
							"a": false,
							"o": false,
							"v": false,
							"d": true,
							"sm": "normal"
						},
						"preview": {
							"transformX": 0,
							"transformY": 0,
							"transformZElevation": 0,
							"transformW": 2.220446049250313e-16,
							"transformH": 2.220446049250313e-16,
							"transformA": 0,
							"transformSX": 0,
							"transformSY": 0,
							"transformO": 0,
							"previewSceneGraph": false
						}
					},
					"instanceFolderItem": {
						"sid": 777789192023907,
						"expanded": true,
						"folderName": "",
						"indexInFolder": -1,
						"folderNestingLevel": -1
					},
					"showing": true,
					"locked": false,
					"world": {
						"x": 745,
						"y": 260,
						"width": 24,
						"height": 92,
						"originX": 0.5,
						"originY": 0,
						"color": [
							1,
							1,
							1,
							0.5
						],
						"angle": 0,
						"zElevation": 0
					}
				},
				{
					"type": "WaterPickup",
					"properties": {
						"initially-visible": false,
						"origin": "top",
						"wrap-horizontal": "repeat",
						"wrap-vertical": "repeat",
						"image-offset-x": 0,
						"image-offset-y": 0,
						"image-scale-x": 1,
						"image-scale-y": 1,
						"image-angle": 0,
						"enable-tile-randomization": false,
						"x-random": 1,
						"y-random": 1,
						"angle-random": 1,
						"blend-margin-x": 0.1,
						"blend-margin-y": 0.1
					},
					"uid": 81,
					"sid": 947609838387523,
					"tags": "",
					"instanceVariables": {},
					"behaviors": {},
					"sceneGraphData": {
						"parent-uid": 75,
						"uid": 81,
						"flags": {
							"x": true,
							"y": true,
							"z": true,
							"w": false,
							"h": false,
							"a": false,
							"o": false,
							"v": false,
							"d": true,
							"sm": "normal"
						},
						"preview": {
							"transformX": 0,
							"transformY": 0,
							"transformZElevation": 0,
							"transformW": 2.220446049250313e-16,
							"transformH": 2.220446049250313e-16,
							"transformA": 0,
							"transformSX": 0,
							"transformSY": 0,
							"transformO": 0,
							"previewSceneGraph": false
						}
					},
					"instanceFolderItem": {
						"sid": 947609838387523,
						"expanded": true,
						"folderName": "",
						"indexInFolder": -1,
						"folderNestingLevel": -1
					},
					"showing": true,
					"locked": false,
					"world": {
						"x": 443,
						"y": 158,
						"width": 24,
						"height": 90,
						"originX": 0.5,
						"originY": 0,
						"color": [
							1,
							1,
							1,
							0.5
						],
						"angle": 0,
						"zElevation": 0
					}
				}
			],
			"sid": 538482151501971,
			"effectTypes": [],
			"isInitiallyVisible": true,
			"isInitiallyInteractive": true,
			"isHTMLElementsLayer": false,
			"color": [
				1,
				1,
				1,
				1
			],
			"backgroundColor": [
				0.30980392156862746,
				0.4823529411764706,
				0.6705882352941176,
				1
			],
			"isTransparent": true,
			"parallaxX": 1,
			"parallaxY": 1,
			"scaleRate": 1,
			"forceOwnTexture": false,
			"renderingMode": "3d",
			"drawOrder": "z-order",
			"useRenderCells": false,
			"blendMode": "normal",
			"zElevation": 0,
			"global": false
		},
		{
			"name": "Lights",
			"overriden": 0,
			"subLayers": [],
			"instances": [
				{
					"type": "Light",
					"properties": {
						"initially-visible": true,
						"initial-animation": "Animation 1",
						"initial-frame": 0,
						"enable-collisions": true,
						"live-preview": false
					},
					"uid": 63,
					"sid": 805464806142722,
					"tags": "",
					"instanceVariables": {},
					"behaviors": {},
					"instanceFolderItem": {
						"sid": 805464806142722,
						"expanded": true,
						"folderName": "",
						"indexInFolder": -1,
						"folderNestingLevel": -1
					},
					"showing": true,
					"locked": false,
					"world": {
						"x": 846,
						"y": 594,
						"width": 882,
						"height": 882,
						"originX": 0.5,
						"originY": 0.5,
						"color": [
							1,
							1,
							1,
							0.6
						],
						"angle": 0,
						"zElevation": 0
					}
				},
				{
					"type": "Light",
					"properties": {
						"initially-visible": true,
						"initial-animation": "Animation 1",
						"initial-frame": 0,
						"enable-collisions": true,
						"live-preview": false
					},
					"uid": 64,
					"sid": 423665779779266,
					"tags": "",
					"instanceVariables": {},
					"behaviors": {},
					"instanceFolderItem": {
						"sid": 423665779779266,
						"expanded": true,
						"folderName": "",
						"indexInFolder": -1,
						"folderNestingLevel": -1
					},
					"showing": true,
					"locked": false,
					"world": {
						"x": 360,
						"y": 414,
						"width": 486,
						"height": 486,
						"originX": 0.5,
						"originY": 0.5,
						"color": [
							1,
							1,
							1,
							0.6
						],
						"angle": 0,
						"zElevation": 0
					}
				},
				{
					"type": "Light",
					"properties": {
						"initially-visible": true,
						"initial-animation": "Animation 1",
						"initial-frame": 0,
						"enable-collisions": true,
						"live-preview": false
					},
					"uid": 65,
					"sid": 563279457272457,
					"tags": "",
					"instanceVariables": {},
					"behaviors": {},
					"instanceFolderItem": {
						"sid": 563279457272457,
						"expanded": true,
						"folderName": "",
						"indexInFolder": -1,
						"folderNestingLevel": -1
					},
					"showing": true,
					"locked": false,
					"world": {
						"x": 414,
						"y": 540,
						"width": 324,
						"height": 486,
						"originX": 0.5,
						"originY": 0.5,
						"color": [
							1,
							1,
							1,
							0.6
						],
						"angle": 0,
						"zElevation": 0
					}
				},
				{
					"type": "Light",
					"properties": {
						"initially-visible": true,
						"initial-animation": "Animation 1",
						"initial-frame": 0,
						"enable-collisions": true,
						"live-preview": false
					},
					"uid": 66,
					"sid": 160487608785913,
					"tags": "",
					"instanceVariables": {},
					"behaviors": {},
					"instanceFolderItem": {
						"sid": 160487608785913,
						"expanded": true,
						"folderName": "",
						"indexInFolder": -1,
						"folderNestingLevel": -1
					},
					"showing": true,
					"locked": false,
					"world": {
						"x": 504,
						"y": 450,
						"width": 414.00000000000006,
						"height": 414.00000000000006,
						"originX": 0.5,
						"originY": 0.5,
						"color": [
							1,
							1,
							1,
							0.6
						],
						"angle": 0.9990098767890556,
						"zElevation": 0
					}
				},
				{
					"type": "Light",
					"properties": {
						"initially-visible": true,
						"initial-animation": "Animation 1",
						"initial-frame": 0,
						"enable-collisions": true,
						"live-preview": false
					},
					"uid": 67,
					"sid": 243199485975177,
					"tags": "",
					"instanceVariables": {},
					"behaviors": {},
					"instanceFolderItem": {
						"sid": 243199485975177,
						"expanded": true,
						"folderName": "",
						"indexInFolder": -1,
						"folderNestingLevel": -1
					},
					"showing": true,
					"locked": false,
					"world": {
						"x": 900,
						"y": 342,
						"width": 414.00000000000006,
						"height": 414.00000000000006,
						"originX": 0.5,
						"originY": 0.5,
						"color": [
							1,
							1,
							1,
							0.6
						],
						"angle": 0.9990098767890556,
						"zElevation": 0
					}
				},
				{
					"type": "Light",
					"properties": {
						"initially-visible": true,
						"initial-animation": "Animation 1",
						"initial-frame": 0,
						"enable-collisions": true,
						"live-preview": false
					},
					"uid": 69,
					"sid": 865755360950079,
					"tags": "",
					"instanceVariables": {},
					"behaviors": {},
					"instanceFolderItem": {
						"sid": 865755360950079,
						"expanded": true,
						"folderName": "",
						"indexInFolder": -1,
						"folderNestingLevel": -1
					},
					"showing": true,
					"locked": false,
					"world": {
						"x": -144,
						"y": 252,
						"width": 1782,
						"height": 1782,
						"originX": 0.5,
						"originY": 0.5,
						"color": [
							1,
							1,
							1,
							0.6
						],
						"angle": 0.9990098767890556,
						"zElevation": 0
					}
				},
				{
					"type": "Light",
					"properties": {
						"initially-visible": true,
						"initial-animation": "Animation 1",
						"initial-frame": 0,
						"enable-collisions": true,
						"live-preview": false
					},
					"uid": 68,
					"sid": 187569456478374,
					"tags": "",
					"instanceVariables": {},
					"behaviors": {},
					"instanceFolderItem": {
						"sid": 187569456478374,
						"expanded": true,
						"folderName": "",
						"indexInFolder": -1,
						"folderNestingLevel": -1
					},
					"showing": true,
					"locked": false,
					"world": {
						"x": 1098,
						"y": 198,
						"width": 1782,
						"height": 1782,
						"originX": 0.5,
						"originY": 0.5,
						"color": [
							1,
							1,
							1,
							0.6
						],
						"angle": 0.9990098767890556,
						"zElevation": 0
					}
				}
			],
			"sid": 768071383874285,
			"effectTypes": [],
			"isInitiallyVisible": true,
			"isInitiallyInteractive": true,
			"isHTMLElementsLayer": false,
			"color": [
				1,
				1,
				1,
				1
			],
			"backgroundColor": [
				0.3686274509803922,
				0.3686274509803922,
				0.3686274509803922,
				1
			],
			"isTransparent": true,
			"parallaxX": 1,
			"parallaxY": 1,
			"scaleRate": 1,
			"forceOwnTexture": false,
			"renderingMode": "3d",
			"drawOrder": "z-order",
			"useRenderCells": false,
			"blendMode": "normal",
			"zElevation": 0,
			"global": false
		},
		{
			"name": "UI",
			"overriden": 0,
			"subLayers": [],
			"instances": [
				{
					"type": "IntroAnim",
					"properties": {
						"initially-visible": false,
						"initial-animation": "Animation 1",
						"initial-frame": 0,
						"enable-collisions": true,
						"live-preview": false
					},
					"uid": 26,
					"sid": 361078118194968,
					"tags": "",
					"instanceVariables": {},
					"behaviors": {},
					"instanceFolderItem": {
						"sid": 361078118194968,
						"expanded": true,
						"folderName": "",
						"indexInFolder": -1,
						"folderNestingLevel": -1
					},
					"showing": true,
					"locked": false,
					"world": {
						"x": 1145,
						"y": 289,
						"width": 274,
						"height": 139,
						"originX": 0.5,
						"originY": 0.5,
						"color": [
							1,
							1,
							1,
							1
						],
						"angle": 0,
						"zElevation": 0
					}
				},
				{
					"type": "GameManager",
					"properties": {
						"initially-visible": true,
						"initial-animation": "Animation 1",
						"initial-frame": 0,
						"enable-collisions": true,
						"live-preview": false
					},
					"uid": 15,
					"sid": 475752144518357,
					"tags": "",
					"instanceVariables": {
						"spawnTrail": false,
						"tutorialOnScreen": true,
						"playerWon": false
					},
					"behaviors": {
						"Tween": {
							"properties": {
								"enabled": true
							}
						}
					},
					"instanceFolderItem": {
						"sid": 475752144518357,
						"expanded": true,
						"folderName": "",
						"indexInFolder": -1,
						"folderNestingLevel": -1
					},
					"showing": true,
					"locked": false,
					"world": {
						"x": -36,
						"y": -36,
						"width": 32,
						"height": 32,
						"originX": 0.5,
						"originY": 0.5,
						"color": [
							1,
							1,
							1,
							1
						],
						"angle": 0,
						"zElevation": 0
					}
				},
				{
					"type": "Fader",
					"properties": {
						"initially-visible": true,
						"origin": "top-left",
						"wrap-horizontal": "repeat",
						"wrap-vertical": "repeat",
						"image-offset-x": 0,
						"image-offset-y": 0,
						"image-scale-x": 1,
						"image-scale-y": 1,
						"image-angle": 0,
						"enable-tile-randomization": false,
						"x-random": 1,
						"y-random": 1,
						"angle-random": 1,
						"blend-margin-x": 0.1,
						"blend-margin-y": 0.1
					},
					"uid": 25,
					"sid": 905402283561940,
					"tags": "",
					"instanceVariables": {},
					"behaviors": {},
					"instanceFolderItem": {
						"sid": 905402283561940,
						"expanded": true,
						"folderName": "",
						"indexInFolder": -1,
						"folderNestingLevel": -1
					},
					"showing": true,
					"locked": false,
					"world": {
						"x": -64,
						"y": -64,
						"width": 1408,
						"height": 848,
						"originX": 0,
						"originY": 0,
						"color": [
							1,
							1,
							1,
							1
						],
						"angle": 0,
						"zElevation": 0
					}
				},
				{
					"type": "TextTutorial",
					"properties": {
						"text": "Reach the top to [color=#ff5555]DEFEAT[/color] the dragon!\n\nHow to play:\n\n- [color=#00aaff]\\[Arrows][/color]: move, jump and climb ladders\n- [color=#00aaff]\\[Space][/color]: throw water to extinguish fire entities\n- [color=#00aaff]\\[Space][/color] next to a stalactite: refill your bucket\n\nPress [color=#00aaff]\\[Space][/color] to start...",
						"enable-bbcode": true,
						"font": "Arial",
						"size": 32,
						"line-height": 0,
						"bold": false,
						"italic": false,
						"color": [
							1,
							1,
							1,
							1
						],
						"horizontal-alignment": "left",
						"vertical-alignment": "top",
						"wrapping": "word",
						"text-direction": "ltr",
						"icon-set": -1,
						"initially-visible": true,
						"origin": "top-left",
						"read-aloud": false
					},
					"uid": 32,
					"sid": 732374437512298,
					"tags": "",
					"instanceVariables": {},
					"behaviors": {
						"Fade": {
							"properties": {
								"fade-in-time": 0.5,
								"wait-time": 0,
								"fade-out-time": 0,
								"destroy": false,
								"enabled": true,
								"live-preview": false
							}
						}
					},
					"instanceFolderItem": {
						"sid": 732374437512298,
						"expanded": true,
						"folderName": "",
						"indexInFolder": -1,
						"folderNestingLevel": -1
					},
					"showing": true,
					"locked": false,
					"world": {
						"x": 181,
						"y": 135,
						"width": 918,
						"height": 450,
						"originX": 0,
						"originY": 0,
						"color": [
							1,
							1,
							1,
							1
						],
						"angle": 0,
						"zElevation": 0
					}
				},
				{
					"type": "TextGameOver",
					"properties": {
						"text": "GAME OVER",
						"enable-bbcode": true,
						"font": "Arial",
						"size": 64,
						"line-height": 0,
						"bold": true,
						"italic": false,
						"color": [
							1,
							0,
							0,
							1
						],
						"horizontal-alignment": "center",
						"vertical-alignment": "center",
						"wrapping": "word",
						"text-direction": "ltr",
						"icon-set": -1,
						"initially-visible": true,
						"origin": "top-left",
						"read-aloud": false
					},
					"uid": 53,
					"sid": 619657726867544,
					"tags": "",
					"instanceVariables": {},
					"behaviors": {},
					"instanceFolderItem": {
						"sid": 619657726867544,
						"expanded": true,
						"folderName": "",
						"indexInFolder": -1,
						"folderNestingLevel": -1
					},
					"showing": true,
					"locked": false,
					"world": {
						"x": 343,
						"y": 279,
						"width": 594,
						"height": 162,
						"originX": 0,
						"originY": 0,
						"color": [
							1,
							1,
							1,
							0
						],
						"angle": 0,
						"zElevation": 0
					}
				},
				{
					"type": "TextPlayerWon",
					"properties": {
						"text": "[outline=#cb3f3f][lineThickness=1.5]They lived happily ever after.[/outline][/lineThickness]\n\n[icon=Heart][icon=Heart][icon=Heart]",
						"enable-bbcode": true,
						"font": "Arial",
						"size": 64,
						"line-height": 0,
						"bold": true,
						"italic": false,
						"color": [
							0.9490196078431372,
							0.47058823529411764,
							0.47058823529411764,
							1
						],
						"horizontal-alignment": "center",
						"vertical-alignment": "center",
						"wrapping": "word",
						"text-direction": "ltr",
						"icon-set": 896592212945411,
						"initially-visible": true,
						"origin": "top-left",
						"read-aloud": false
					},
					"uid": 57,
					"sid": 222585968026381,
					"tags": "",
					"instanceVariables": {},
					"behaviors": {},
					"instanceFolderItem": {
						"sid": 222585968026381,
						"expanded": true,
						"folderName": "",
						"indexInFolder": -1,
						"folderNestingLevel": -1
					},
					"showing": true,
					"locked": false,
					"world": {
						"x": 271,
						"y": 171,
						"width": 738,
						"height": 378,
						"originX": 0,
						"originY": 0,
						"color": [
							1,
							1,
							1,
							0
						],
						"angle": 0,
						"zElevation": 0
					}
				},
				{
					"type": "Heart",
					"properties": {
						"initially-visible": true,
						"initial-animation": "Animation 1",
						"initial-frame": 0,
						"enable-collisions": true,
						"live-preview": false
					},
					"uid": 58,
					"sid": 264001402908146,
					"tags": "",
					"instanceVariables": {},
					"behaviors": {},
					"instanceFolderItem": {
						"sid": 264001402908146,
						"expanded": true,
						"folderName": "",
						"indexInFolder": -1,
						"folderNestingLevel": -1
					},
					"showing": false,
					"locked": false,
					"world": {
						"x": -234,
						"y": -216,
						"width": 330,
						"height": 300,
						"originX": 0.5,
						"originY": 0.5,
						"color": [
							1,
							1,
							1,
							1
						],
						"angle": 0,
						"zElevation": 0
					}
				}
			],
			"sid": 854695268597451,
			"effectTypes": [],
			"isInitiallyVisible": true,
			"isInitiallyInteractive": true,
			"isHTMLElementsLayer": false,
			"color": [
				1,
				1,
				1,
				1
			],
			"backgroundColor": [
				0.3686274509803922,
				0.3686274509803922,
				0.3686274509803922,
				1
			],
			"isTransparent": true,
			"parallaxX": 0,
			"parallaxY": 0,
			"scaleRate": 1,
			"forceOwnTexture": false,
			"renderingMode": "3d",
			"drawOrder": "z-order",
			"useRenderCells": false,
			"blendMode": "normal",
			"zElevation": 0,
			"global": false
		}
	],
	"scene-graphs-folder-root": {
		"items": [],
		"subfolders": []
	},
	"sid": 407124232216682,
	"nonworld-instances": [],
	"effectTypes": [],
	"width": 1280,
	"height": 720,
	"unboundedScrolling": true,
	"vpX": 0.5,
	"vpY": 0.5,
	"projection": "perspective",
	"eventSheet": "Events"
}