{
	"name": "Trail",
	"plugin-id": "Sprite",
	"sid": 726810839982669,
	"isGlobal": false,
	"instanceVariables": [],
	"behaviorTypes": [],
	"effectTypes": [],
	"animations": {
		"items": [
			{
				"frames": [
					{
						"width": 64,
						"height": 64,
						"originX": 0.5,
						"originY": 1,
						"originalSource": "",
						"exportFormat": "png",
						"exportQuality": 0.8,
						"imageSpriteId": 415030,
						"useCollisionPoly": true,
						"duration": 1
					},
					{
						"width": 64,
						"height": 64,
						"originX": 0.5,
						"originY": 1,
						"originalSource": "",
						"exportFormat": "png",
						"exportQuality": 0.8,
						"imageSpriteId": 302416,
						"useCollisionPoly": true,
						"duration": 1
					},
					{
						"width": 64,
						"height": 64,
						"originX": 0.5,
						"originY": 1,
						"originalSource": "",
						"exportFormat": "png",
						"exportQuality": 0.8,
						"imageSpriteId": 1986766,
						"useCollisionPoly": true,
						"duration": 1
					},
					{
						"width": 64,
						"height": 64,
						"originX": 0.5,
						"originY": 1,
						"originalSource": "",
						"exportFormat": "png",
						"exportQuality": 0.8,
						"imageSpriteId": 5300030,
						"useCollisionPoly": true,
						"duration": 1
					},
					{
						"width": 64,
						"height": 64,
						"originX": 0.5,
						"originY": 1,
						"originalSource": "",
						"exportFormat": "png",
						"exportQuality": 0.8,
						"imageSpriteId": 631863,
						"useCollisionPoly": true,
						"duration": 1
					}
				],
				"sid": 256286139604076,
				"name": "Default",
				"isLooping": false,
				"isPingPong": false,
				"repeatCount": 1,
				"repeatTo": 0,
				"speed": 15
			}
		],
		"subfolders": []
	}
}